key_expansion.v
module keyexpansion (
    input wire [255:0] key,
    input wire clk,
    input wire rst,
    output reg [127:0] out_key
);
    reg [255:0] key_in;

	reg [7:0] g0,g1,g2,g3;
    reg [31:0] temp,temp2,word,rot,sub,round_constant,word_1,word_2,word_3,word_4,word_5,word_6,word_7,word_8 =32'b0;
    reg [1:0] sub_counter,second_subcounter =2'b00;
    reg [4:0] state,nextstate =5'b00000;
    reg [3:0] word_counter=4'b0000;
	reg [3:0] rounds_counter=4'b0000;
   localparam  IDLE=5'b00001 ; 
   localparam  START=5'b00010 ; 
   localparam  EXPANSION=5'b00011 ; 
   localparam  ROT_BYTE=5'b00100 ; 
   localparam  SUB_BYTE=5'b00101 ; 
   localparam  RC_CON=5'b00110 ; 
   localparam  XOR=5'b00111 ; 
   localparam ROUND_1 =5'b01000 ;
   localparam ROUND_2 =5'b01001 ;
   localparam   DONE=5'b01010 ; 
    
   always @(posedge clk ) begin
    if (rst) begin
        state <= IDLE ;

   end
   else begin
        state <= nextstate;
        word_counter =word_counter+1;
        sub_counter =sub_counter +1;
   end
   end
    always @(*) begin
		second_subcounter=sub_counter;
     case (state)
        IDLE:begin
			 second_subcounter=2'b0;
            nextstate=START;
			 
        end
      START:begin 
        key_in=key;
		// second_subcounter=sub_counter;
        nextstate=EXPANSION;
      end
      EXPANSION:begin 
		// second_subcounter =2'b00;
		// sub_counter =2'b00;
		//   second_subcounter=2'b00;
        if (word_counter== 4'b0100)
        out_key=key_in [127:0];
        if (word_counter ==4'b1000) begin
            out_key=key_in[255:128];
            temp = key_in[255:224];
            if(word_counter %8==0) begin
                //   rounds_counter=rounds_counter+1;
				nextstate=ROT_BYTE;
		if(word_counter%8==0)begin
			
		end	
			end
		// if(round_counter==1'b1)	
		// 	nextstate=ROUND_1;
		// 	if(word_counter%8==0)begin
        // end
        
      end
	  
      end
      ROT_BYTE:begin
		// second_subcounter =2'b00;
       sub_counter =2'b00;
         rot ={temp[23:0],temp[31:24]};
		// g0=temp[15:8];
		// g1=temp[23:16];
		// g2=temp[31:24];
		// g3=temp[7:0];

        nextstate=SUB_BYTE;

        end
       SUB_BYTE:begin
		
         if (second_subcounter <= 2'b11)begin
        //  if (secon_counter  <= 2'b11)begin
			 
        case (rot[7:0])
            8'h00: sub=8'h63;
	   8'h01: sub=8'h7c;
	   8'h02: sub=8'h77;
	   8'h03: sub=8'h7b;
	   8'h04: sub=8'hf2;
	   8'h05: sub=8'h6b;
	   8'h06: sub=8'h6f;
	   8'h07: sub=8'hc5;
	   8'h08: sub=8'h30;
	   8'h09: sub=8'h01;
	   8'h0a: sub=8'h67;
	   8'h0b: sub=8'h2b;
	   8'h0c: sub=8'hfe;
	   8'h0d: sub=8'hd7;
	   8'h0e: sub=8'hab;
	   8'h0f: sub=8'h76;
	   8'h10: sub=8'hca;
	   8'h11: sub=8'h82;
	   8'h12: sub=8'hc9;
	   8'h13: sub=8'h7d;
	   8'h14: sub=8'hfa;
	   8'h15: sub=8'h59;
	   8'h16: sub=8'h47;
	   8'h17: sub=8'hf0;
	   8'h18: sub=8'had;
	   8'h19: sub=8'hd4;
	   8'h1a: sub=8'ha2;
	   8'h1b: sub=8'haf;
	   8'h1c: sub=8'h9c;
	   8'h1d: sub=8'ha4;
	   8'h1e: sub=8'h72;
	   8'h1f: sub=8'hc0;
	   8'h20: sub=8'hb7;
	   8'h21: sub=8'hfd;
	   8'h22: sub=8'h93;
	   8'h23: sub=8'h26;
	   8'h24: sub=8'h36;
	   8'h25: sub=8'h3f;
	   8'h26: sub=8'hf7;
	   8'h27: sub=8'hcc;
	   8'h28: sub=8'h34;
	   8'h29: sub=8'ha5;
	   8'h2a: sub=8'he5;
	   8'h2b: sub=8'hf1;
	   8'h2c: sub=8'h71;
	   8'h2d: sub=8'hd8;
	   8'h2e: sub=8'h31;
	   8'h2f: sub=8'h15;
	   8'h30: sub=8'h04;
	   8'h31: sub=8'hc7;
	   8'h32: sub=8'h23;
	   8'h33: sub=8'hc3;
	   8'h34: sub=8'h18;
	   8'h35: sub=8'h96;
	   8'h36: sub=8'h05;
	   8'h37: sub=8'h9a;
	   8'h38: sub=8'h07;
	   8'h39: sub=8'h12;
	   8'h3a: sub=8'h80;
	   8'h3b: sub=8'he2;
	   8'h3c: sub=8'heb;
	   8'h3d: sub=8'h27;
	   8'h3e: sub=8'hb2;
	   8'h3f: sub=8'h75;
	   8'h40: sub=8'h09;
	   8'h41: sub=8'h83;
	   8'h42: sub=8'h2c;
	   8'h43: sub=8'h1a;
	   8'h44: sub=8'h1b;
	   8'h45: sub=8'h6e;
	   8'h46: sub=8'h5a;
	   8'h47: sub=8'ha0;
	   8'h48: sub=8'h52;
	   8'h49: sub=8'h3b;
	   8'h4a: sub=8'hd6;
	   8'h4b: sub=8'hb3;
	   8'h4c: sub=8'h29;
	   8'h4d: sub=8'he3;
	   8'h4e: sub=8'h2f;
	   8'h4f: sub=8'h84;
	   8'h50: sub=8'h53;
	   8'h51: sub=8'hd1;
	   8'h52: sub=8'h00;
	   8'h53: sub=8'hed;
	   8'h54: sub=8'h20;
	   8'h55: sub=8'hfc;
	   8'h56: sub=8'hb1;
	   8'h57: sub=8'h5b;
	   8'h58: sub=8'h6a;
	   8'h59: sub=8'hcb;
	   8'h5a: sub=8'hbe;
	   8'h5b: sub=8'h39;
	   8'h5c: sub=8'h4a;
	   8'h5d: sub=8'h4c;
	   8'h5e: sub=8'h58;
	   8'h5f: sub=8'hcf;
	   8'h60: sub=8'hd0;
	   8'h61: sub=8'hef;
	   8'h62: sub=8'haa;
	   8'h63: sub=8'hfb;
	   8'h64: sub=8'h43;
	   8'h65: sub=8'h4d;               

	   8'h66: sub=8'h33;
	   8'h67: sub=8'h85;
	   8'h68: sub=8'h45;
	   8'h69: sub=8'hf9;
	   8'h6a: sub=8'h02;
	   8'h6b: sub=8'h7f;
	   8'h6c: sub=8'h50;
	   8'h6d: sub=8'h3c;
	   8'h6e: sub=8'h9f;
	   8'h6f: sub=8'ha8;
	   8'h70: sub=8'h51;
	   8'h71: sub=8'ha3;
	   8'h72: sub=8'h40;
	   8'h73: sub=8'h8f;
	   8'h74: sub=8'h92;
	   8'h75: sub=8'h9d;
	   8'h76: sub=8'h38;
	   8'h77: sub=8'hf5;
	   8'h78: sub=8'hbc;
	   8'h79: sub=8'hb6;
	   8'h7a: sub=8'hda;
	   8'h7b: sub=8'h21;
	   8'h7c: sub=8'h10;
	   8'h7d: sub=8'hff;
	   8'h7e: sub=8'hf3;
	   8'h7f: sub=8'hd2;
	   8'h80: sub=8'hcd;
	   8'h81: sub=8'h0c;
	   8'h82: sub=8'h13;
	   8'h83: sub=8'hec;
	   8'h84: sub=8'h5f;
	   8'h85: sub=8'h97;
	   8'h86: sub=8'h44;
	   8'h87: sub=8'h17;
	   8'h88: sub=8'hc4;
	   8'h89: sub=8'ha7;
	   8'h8a: sub=8'h7e;
	   8'h8b: sub=8'h3d;
	   8'h8c: sub=8'h64;
	   8'h8d: sub=8'h5d;
	   8'h8e: sub=8'h19;
	   8'h8f: sub=8'h73;
	   8'h90: sub=8'h60;
	   8'h91: sub=8'h81;
	   8'h92: sub=8'h4f;
	   8'h93: sub=8'hdc;
	   8'h94: sub=8'h22;
	   8'h95: sub=8'h2a;
	   8'h96: sub=8'h90;
	   8'h97: sub=8'h88;
	   8'h98: sub=8'h46;
	   8'h99: sub=8'hee;
	   8'h9a: sub=8'hb8;
	   8'h9b: sub=8'h14;
	   8'h9c: sub=8'hde;
	   8'h9d: sub=8'h5e;
	   8'h9e: sub=8'h0b;
	   8'h9f: sub=8'hdb;
	   8'ha0: sub=8'he0;
	   8'ha1: sub=8'h32;
	   8'ha2: sub=8'h3a;
	   8'ha3: sub=8'h0a;
	   8'ha4: sub=8'h49;
	   8'ha5: sub=8'h06;
	   8'ha6: sub=8'h24;
	   8'ha7: sub=8'h5c;
	   8'ha8: sub=8'hc2;
	   8'ha9: sub=8'hd3;
	   8'haa: sub=8'hac;
	   8'hab: sub=8'h62;
	   8'hac: sub=8'h91;
	   8'had: sub=8'h95;
	   8'hae: sub=8'he4;
	   8'haf: sub=8'h79;
	   8'hb0: sub=8'he7;
	   8'hb1: sub=8'hc8;
	   8'hb2: sub=8'h37;
	   8'hb3: sub=8'h6d;
	   8'hb4: sub=8'h8d;
	   8'hb5: sub=8'hd5;
	   8'hb6: sub=8'h4e;
	   8'hb7: sub=8'ha9;
	   8'hb8: sub=8'h6c;
	   8'hb9: sub=8'h56;
	   8'hba: sub=8'hf4;
	   8'hbb: sub=8'hea;
	   8'hbc: sub=8'h65;
	   8'hbd: sub=8'h7a;
	   8'hbe: sub=8'hae;
	   8'hbf: sub=8'h08;
	   8'hc0: sub=8'hba;
	   8'hc1: sub=8'h78;
	   8'hc2: sub=8'h25;
	   8'hc3: sub=8'h2e;
	   8'hc4: sub=8'h1c;
	   8'hc5: sub=8'ha6;
	   8'hc6: sub=8'hb4;
	   8'hc7: sub=8'hc6;
	   8'hc8: sub=8'he8;
	   8'hc9: sub=8'hdd;
	   8'hca: sub=8'h74;
	   8'hcb: sub=8'h1f;
	   8'hcc: sub=8'h4b;
	   8'hcd: sub=8'hbd;
	   8'hce: sub=8'h8b;
	   8'hcf: sub=8'h8a;
	   8'hd0: sub=8'h70;
	   8'hd1: sub=8'h3e;
	   8'hd2: sub=8'hb5;
	   8'hd3: sub=8'h66;
	   8'hd4: sub=8'h48;
	   8'hd5: sub=8'h03;
	   8'hd6: sub=8'hf6;
	   8'hd7: sub=8'h0e;
	   8'hd8: sub=8'h61;
	   8'hd9: sub=8'h35;
	   8'hda: sub=8'h57;
	   8'hdb: sub=8'hb9;
	   8'hdc: sub=8'h86;
	   8'hdd: sub=8'hc1;
	   8'hde: sub=8'h1d;
	   8'hdf: sub=8'h9e;
	   8'he0: sub=8'he1;
	   8'he1: sub=8'hf8;
	   8'he2: sub=8'h98;
	   8'he3: sub=8'h11;
	   8'he4: sub=8'h69;
	   8'he5: sub=8'hd9;
	   8'he6: sub=8'h8e;
	   8'he7: sub=8'h94;
	   8'he8: sub=8'h9b;
	   8'he9: sub=8'h1e;
	   8'hea: sub=8'h87;
	   8'heb: sub=8'he9;
	   8'hec: sub=8'hce;
	   8'hed: sub=8'h55;
	   8'hee: sub=8'h28;
	   8'hef: sub=8'hdf;
	   8'hf0: sub=8'h8c;
	   8'hf1: sub=8'ha1;
	   8'hf2: sub=8'h89;
	   8'hf3: sub=8'h0d;
	   8'hf4: sub=8'hbf;
	   8'hf5: sub=8'he6;
	   8'hf6: sub=8'h42;
	   8'hf7: sub=8'h68;
	   8'hf8: sub=8'h41;
	   8'hf9: sub=8'h99;
	   8'hfa: sub=8'h2d;
	   8'hfb: sub=8'h0f;
	   8'hfc: sub=8'hb0;
	   8'hfd: sub=8'h54;
	   8'hfe: sub=8'hbb;
	   8'hff: sub=8'h16;  
        endcase
        rot =rot>>8;
		//  temp2={temp2[31:8],sub[7:0]};
		//  temp2=temp2>>8;
		  temp2={sub[7:0],temp2[31:8]};
		// temp2=temp<<8;
		// if(sub)begin
			
	
		// sub_counter=sub_counter+1;
		// end
		temp =temp<<8;
		        //  sub_counter =sub_counter +1;

        end
    	if(word_counter==4'hc)	 begin
			
		
	  nextstate=RC_CON;
		end
    end
	RC_CON:begin
		// if(round_counter ==1)
		// round_counstant=round_constant{temp2[31:24]^8'h01:temp2[23:0]};
		// round_counstant=round_counstant
		 
		//  g0 = temp2[31:24] ^ 8'h01;
		 round_constant = {temp2[31:24] ^ 8'h01, temp2[23:0]};

		                  rounds_counter=rounds_counter+4'b1;


	end	
    

	ROUND_1:begin
		if(rounds_counter==1'b1)begin
		word=key_in;
		end

		// if(word_counter %8==0) begin
        //         //   rounds_counter=rounds_counter+1;
		// 		nextstate=ROT_BYTE;
		// if(word_counter %8==4) begin
        //         //   rounds_counter=rounds_counter+1;
		// 		nextstate=ROT_BYTE;

		word_1=round_constant^word[31:0];
		word_2=word_1^word[63:32];
		word_3=word_2^word[95:64];
		word_4=word_3^word[127:96];
	
		// W9=W8^key_in[63:32];
		// W10=W9^key_in[95:64];
		// W11=W10^key_in[127:96];
		// W12=
		end
		endcase
	end
        
	
		// end
    

    
endmodule

key_expansion_tb.v
module tb_keyexpansion;

    // Testbench signals
    reg clk;
    reg rst;
    reg [255:0] key;
    wire [127:0] out_key;

    // Instantiate the keyexpansion module
    keyexpansion uut (
        .key(key),
        .clk(clk),
        .rst(rst),
        .out_key(out_key)
    );

    // Clock generation
    initial begin
        clk = 0;
        forever #5 clk = ~clk; // 10ns period
    end

    // Test sequence
    initial begin
        // Initialize inputs
        rst = 1;
        key = 256'h642423baa95efb4362d3f2ce993c0904150f258aa1fe796841d7b4429c9b5a30
;

        // Reset the system
        #10;
        rst = 0;
        #10;
        // rst = 1;

        // Apply test vectors
        #160; // Run simulation for some time

        // End simulation
        $finish;
        
    end

    // Waveform dump
    initial begin
        $dumpfile("keyexpansion.vcd");
        $dumpvars(0, tb_keyexpansion);
    end

endmodule

keyexpansion.vcd
$date
	Fri Jul 19 19:11:55 2024
$end
$version
	Icarus Verilog
$end
$timescale
	1s
$end
$scope module tb_keyexpansion $end
$var wire 128 ! out_key [127:0] $end
$var reg 1 " clk $end
$var reg 256 # key [255:0] $end
$var reg 1 $ rst $end
$scope module uut $end
$var wire 1 " clk $end
$var wire 256 % key [255:0] $end
$var wire 1 $ rst $end
$var parameter 5 & DONE $end
$var parameter 5 ' EXPANSION $end
$var parameter 5 ( IDLE $end
$var parameter 5 ) RC_CON $end
$var parameter 5 * ROT_BYTE $end
$var parameter 5 + ROUND_1 $end
$var parameter 5 , ROUND_2 $end
$var parameter 5 - START $end
$var parameter 5 . SUB_BYTE $end
$var parameter 5 / XOR $end
$var reg 256 0 key_in [255:0] $end
$var reg 5 1 nextstate [4:0] $end
$var reg 128 2 out_key [127:0] $end
$var reg 32 3 rot [31:0] $end
$var reg 32 4 round_constant [31:0] $end
$var reg 4 5 rounds_counter [3:0] $end
$var reg 2 6 second_subcounter [1:0] $end
$var reg 5 7 state [4:0] $end
$var reg 32 8 sub [31:0] $end
$var reg 2 9 sub_counter [1:0] $end
$var reg 32 : temp [31:0] $end
$var reg 32 ; temp2 [31:0] $end
$var reg 32 < word [31:0] $end
$var reg 32 = word_1 [31:0] $end
$var reg 32 > word_2 [31:0] $end
$var reg 32 ? word_3 [31:0] $end
$var reg 32 @ word_4 [31:0] $end
$var reg 32 A word_8 [31:0] $end
$var reg 4 B word_counter [3:0] $end
$upscope $end
$upscope $end
$enddefinitions $end
$comment Show the parameter values. $end
$dumpall
b111 /
b101 .
b10 -
b1001 ,
b1000 +
b100 *
b110 )
b1 (
b11 '
b1010 &
$end
#0
$dumpvars
b0 B
b0 A
bx @
bx ?
bx >
bx =
bx <
bx ;
bx :
bx 9
bx 8
bx 7
bx 6
b0 5
bx 4
bx 3
bx 2
b0 1
bx 0
b110010000100100001000111011101010101001010111101111101101000011011000101101001111110010110011101001100100111100000010010000010000010101000011110010010110001010101000011111111001111001011010000100000111010111101101000100001010011100100110110101101000110000 %
1$
b110010000100100001000111011101010101001010111101111101101000011011000101101001111110010110011101001100100111100000010010000010000010101000011110010010110001010101000011111111001111001011010000100000111010111101101000100001010011100100110110101101000110000 #
0"
bx !
$end
#5
b10 1
b0 6
b1 7
1"
#10
0"
0$
#15
b11 1
b110010000100100001000111011101010101001010111101111101101000011011000101101001111110010110011101001100100111100000010010000010000010101000011110010010110001010101000011111111001111001011010000100000111010111101101000100001010011100100110110101101000110000 0
b10 7
bx 6
b1 B
1"
#20
0"
#25
b11 7
b10 B
1"
#30
0"
#35
b11 B
1"
#40
0"
#45
b10101000011110010010110001010101000011111111001111001011010000100000111010111101101000100001010011100100110110101101000110000 !
b10101000011110010010110001010101000011111111001111001011010000100000111010111101101000100001010011100100110110101101000110000 2
b100 B
1"
#50
0"
#55
b101 B
1"
#60
0"
#65
b110 B
1"
#70
0"
#75
b111 B
1"
#80
0"
#85
b100 1
b1100100001001000010001110111010 :
b1100100001001000010001110111010101010010101111011111011010000110110001011010011111100101100111010011001001111000000100100000100 !
b1100100001001000010001110111010101010010101111011111011010000110110001011010011111100101100111010011001001111000000100100000100 2
b1000 B
1"
#90
0"
#95
b101 1
b100100001000111011101001100100 3
b0 9
b100 7
b1001 B
1"
#100
0"
#105
b100100001000111011101000000000 :
b1000011xxxxxxxxxxxxxxxxxxxxxxxx ;
b1001000010001110111010 3
b1000011 8
b101 7
b0 6
b0 9
b1010 B
1"
#110
0"
#115
b100011101110100000000000000000 :
b1111010001000011xxxxxxxxxxxxxxxx ;
b10010000100011 3
b11110100 8
b1 6
b1 9
b1011 B
1"
#120
0"
#125
b110 1
b10111010000000000000000000000000 :
b1001101111010001000011xxxxxxxx ;
b100100 3
b100110 8
b10 6
b10 9
b1100 B
1"
#130
0"
#135
b1 5
b110111001001101111010001000011 4
b110 7
b0 :
b110110001001101111010001000011 ;
b0 3
b110110 8
b11 6
b11 9
b1101 B
1"
#140
0"
#145
b10 5
b0 6
b0 9
b1110 B
1"
#150
0"
#155
b11 5
b1 6
b1 9
b1111 B
1"
#160
0"
#165
b100 5
b10 6
b10 9
b0 B
1"
#170
0"
#175
b101 5
b11 6
b11 9
b1 B
1"
