updatedkeyexpansion.v
module updatedkeyexpansion (
    input wire [255:0] key,
    input wire clk,
    input wire rst,
    output reg [127:0] out_key


);  reg [255:0] key_in,word;
    reg [127:0] expansion1,expansion2,expansion3,expansion4,round1_result,round2_result,round3_result,round4_result,round5_result,round6_result,round7_result,round8_result,round9_result,round10_result,round11_result,round12_result,round13_result,round14_result,round15_result;
	reg expansion3_enable,expansion4_enable;
    reg [31:0] temp,temp2,rot,sub,round_constant=32'b0;
    reg [1:0] sub_counter,second_subcounter =2'b00;
    reg [4:0] state,nextstate =4'b0000;
    reg [3:0] word_counter,sub_roundcounter=4'b0000;
	reg [3:0] rounds_counter=4'b0000;

   localparam  IDLE=4'b0001 ;
   localparam  START=4'b0010 ;
   localparam  EXPANSION_1=4'b0011 ;
   localparam  EXPANSION_2=4'b0100 ;
   localparam  EXPANSION_3=4'b0101 ;
   localparam  EXPANSION_4=4'b0110 ;
   localparam  ROT_BYTE=4'b0111 ;
   localparam  SUB_BYTE=4'b1000 ;
   localparam  RC_CON=4'b1001 ;
   localparam  XOR=4'b1010 ;


always @(posedge clk) begin
        if (rst) begin
            state <= IDLE;
            word_counter <= 4'b0000;
            
            sub_counter <= 2'b00;
        end 
		else begin
            state <= nextstate;
            word_counter <= word_counter + 1;
            sub_counter <= sub_counter + 1;
           
        end
    end
always @(*) begin
    second_subcounter = sub_counter;
    case (state)
        IDLE: begin
            nextstate = START;
        end

        START: begin
            key_in = key;
            nextstate = EXPANSION_1;
        end

        EXPANSION_1: begin
			sub_roundcounter = sub_roundcounter + 1;
            if (rounds_counter == 1'h0) begin
                expansion1 = key_in[127:0];
                round1_result = expansion1;
				nextstate=EXPANSION_2;
            end 
		
			else begin
			if(sub_roundcounter == 4'h5) begin
                expansion1[31:0]   = round3_result[31:0] ^ temp2;
                expansion1[63:32]  = round3_result[63:32] ^ expansion1[31:0];
                expansion1[95:64]  = round3_result[95:64] ^ expansion1[63:32];
                expansion1[127:96] = round3_result[127:96] ^ expansion1[95:64];
				round5_result=expansion1;
				rot = round5_result[127:96];
                second_subcounter=2'h0;
				nextstate =SUB_BYTE;
            end
			end
		end
		EXPANSION_2: begin 	
			sub_roundcounter=sub_roundcounter+1;
            if (sub_roundcounter == 4'h2) begin
                expansion2 = key_in[256:128];
                temp = expansion2[127:96];
                round2_result = expansion2;
            end

            
            nextstate = ROT_BYTE;
        end

        ROT_BYTE: begin
            sub_counter = 2'b00;
            rot = {temp[23:0], temp[31:24]};
            nextstate = SUB_BYTE;
        end
       SUB_BYTE: begin
                
                 
                    case (rot[7:0])
                        8'h00: sub = 8'h63; 8'h01: sub = 8'h7c; 8'h02: sub = 8'h77; 8'h03: sub = 8'h7b;
                        8'h04: sub = 8'hf2; 8'h05: sub = 8'h6b; 8'h06: sub = 8'h6f; 8'h07: sub = 8'hc5;
                        8'h08: sub = 8'h30; 8'h09: sub = 8'h01; 8'h0a: sub = 8'h67; 8'h0b: sub = 8'h2b;
                        8'h0c: sub = 8'hfe; 8'h0d: sub = 8'hd7; 8'h0e: sub = 8'hab; 8'h0f: sub = 8'h76;
                        8'h10: sub = 8'hca; 8'h11: sub = 8'h82; 8'h12: sub = 8'hc9; 8'h13: sub = 8'h7d;
                        8'h14: sub = 8'hfa; 8'h15: sub = 8'h59; 8'h16: sub = 8'h47; 8'h17: sub = 8'hf0;
                        8'h18: sub = 8'had; 8'h19: sub = 8'hd4; 8'h1a: sub = 8'ha2; 8'h1b: sub = 8'haf;
                        8'h1c: sub = 8'h9c; 8'h1d: sub = 8'ha4; 8'h1e: sub = 8'h72; 8'h1f: sub = 8'hc0;
                        8'h20: sub = 8'hb7; 8'h21: sub = 8'hfd; 8'h22: sub = 8'h93; 8'h23: sub = 8'h26;
                        8'h24: sub = 8'h36; 8'h25: sub = 8'h3f; 8'h26: sub = 8'hf7; 8'h27: sub = 8'hcc;
                        8'h28: sub = 8'h34; 8'h29: sub = 8'ha5; 8'h2a: sub = 8'he5; 8'h2b: sub = 8'hf1;
                        8'h2c: sub = 8'h71; 8'h2d: sub = 8'hd8; 8'h2e: sub = 8'h31; 8'h2f: sub = 8'h15;
                        8'h30: sub = 8'h04; 8'h31: sub = 8'hc7; 8'h32: sub = 8'h23; 8'h33: sub = 8'hc3;
                        8'h34: sub = 8'h18; 8'h35: sub = 8'h96; 8'h36: sub = 8'h05; 8'h37: sub = 8'h9a;
                        8'h38: sub = 8'h07; 8'h39: sub = 8'h12; 8'h3a: sub = 8'h80; 8'h3b: sub = 8'he2;
                        8'h3c: sub = 8'heb; 8'h3d: sub = 8'h27; 8'h3e: sub = 8'hb2; 8'h3f: sub = 8'h75;
                        8'h40: sub = 8'h09; 8'h41: sub = 8'h83; 8'h42: sub = 8'h2c; 8'h43: sub = 8'h1a;
                        8'h44: sub = 8'h1b; 8'h45: sub = 8'h6e; 8'h46: sub = 8'h5a; 8'h47: sub = 8'ha0;
                        8'h48: sub = 8'h52; 8'h49: sub = 8'h3b; 8'h4a: sub = 8'hd6; 8'h4b: sub = 8'hb3;
                        8'h4c: sub = 8'h29; 8'h4d: sub = 8'he3; 8'h4e: sub = 8'h2f; 8'h4f: sub = 8'h84;
                        8'h50: sub = 8'h53; 8'h51: sub = 8'hd1; 8'h52: sub = 8'h00; 8'h53: sub = 8'hed;
                        8'h54: sub = 8'h20; 8'h55: sub = 8'hfc; 8'h56: sub = 8'hb1; 8'h57: sub = 8'h5b;
                        8'h58: sub = 8'h6a; 8'h59: sub = 8'hcb; 8'h5a: sub = 8'hbe; 8'h5b: sub = 8'h39;
                        8'h5c: sub = 8'h4a; 8'h5d: sub = 8'h4c; 8'h5e: sub = 8'h58; 8'h5f: sub = 8'hcf;
                        8'h60: sub = 8'hd0; 8'h61: sub = 8'hef; 8'h62: sub = 8'haa; 8'h63: sub = 8'hfb;
                        8'h64: sub = 8'h43; 8'h65: sub = 8'h4d; 8'h66: sub = 8'h33; 8'h67: sub = 8'h85;
                        8'h68: sub = 8'h45; 8'h69: sub = 8'hf9; 8'h6a: sub = 8'h02; 8'h6b: sub = 8'h7f;
                        8'h6c: sub = 8'h50; 8'h6d: sub = 8'h3c; 8'h6e: sub = 8'h9f; 8'h6f: sub = 8'ha8;
                        8'h70: sub = 8'h51; 8'h71: sub = 8'ha3; 8'h72: sub = 8'h40; 8'h73: sub = 8'h8f;
                        8'h74: sub = 8'h92; 8'h75: sub = 8'h9d; 8'h76: sub = 8'h38; 8'h77: sub = 8'hf5;
                        8'h78: sub = 8'hbc; 8'h79: sub = 8'hb6; 8'h7a: sub = 8'hda; 8'h7b: sub = 8'h21;
                        8'h7c: sub = 8'h10; 8'h7d: sub = 8'hff; 8'h7e: sub = 8'hf3; 8'h7f: sub = 8'hd2;
                        8'h80: sub = 8'hcd; 8'h81: sub = 8'h0c; 8'h82: sub = 8'h13; 8'h83: sub = 8'hec;
                        8'h84: sub = 8'h5f; 8'h85: sub = 8'h97; 8'h86: sub = 8'h44; 8'h87: sub = 8'h17;
                        8'h88: sub = 8'hc4; 8'h89: sub = 8'ha7; 8'h8a: sub = 8'h7e; 8'h8b: sub = 8'h3d;
                        8'h8c: sub = 8'h64; 8'h8d: sub = 8'h5d; 8'h8e: sub = 8'h19; 8'h8f: sub = 8'h73;
                        8'h90: sub = 8'h60; 8'h91: sub = 8'h81; 8'h92: sub = 8'h4f; 8'h93: sub = 8'hdc;
                        8'h94: sub = 8'h22; 8'h95: sub = 8'h2a; 8'h96: sub = 8'h90; 8'h97: sub = 8'h88;
                        8'h98: sub = 8'h46; 8'h99: sub = 8'hee; 8'h9a: sub = 8'hb8; 8'h9b: sub = 8'h14;
                        8'h9c: sub = 8'hde; 8'h9d: sub = 8'h5e; 8'h9e: sub = 8'h0b; 8'h9f: sub = 8'hdb;
                        8'ha0: sub = 8'he0; 8'ha1: sub = 8'h32; 8'ha2: sub = 8'h3a; 8'ha3: sub = 8'h0a;
                        8'ha4: sub = 8'h49; 8'ha5: sub = 8'h06; 8'ha6: sub = 8'h24; 8'ha7: sub = 8'h5c;
                        8'ha8: sub = 8'hc2; 8'ha9: sub = 8'hd3; 8'haa: sub = 8'hac; 8'hab: sub = 8'h62;
                        8'hac: sub = 8'h91; 8'had: sub = 8'h95; 8'hae: sub = 8'he4; 8'haf: sub = 8'h79;
                        8'hb0: sub = 8'he7; 8'hb1: sub = 8'hc8; 8'hb2: sub = 8'h37; 8'hb3: sub = 8'h6d;
                        8'hb4: sub = 8'h8d; 8'hb5: sub = 8'hd5; 8'hb6: sub = 8'h4e; 8'hb7: sub = 8'ha9;
                        8'hb8: sub = 8'h6c; 8'hb9: sub = 8'h56; 8'hba: sub = 8'hf4; 8'hbb: sub = 8'hea;
                        8'hbc: sub = 8'h65; 8'hbd: sub = 8'h7a; 8'hbe: sub = 8'hae; 8'hbf: sub = 8'h08;
                        8'hc0: sub = 8'hba; 8'hc1: sub = 8'h78; 8'hc2: sub = 8'h25; 8'hc3: sub = 8'h2e;
                        8'hc4: sub = 8'h1c; 8'hc5: sub = 8'ha6; 8'hc6: sub = 8'hb4; 8'hc7: sub = 8'hc6;
                        8'hc8: sub = 8'he8; 8'hc9: sub = 8'hdd; 8'hca: sub = 8'h74; 8'hcb: sub = 8'h1f;
                        8'hcc: sub = 8'h4b; 8'hcd: sub = 8'hbd; 8'hce: sub = 8'h8b; 8'hcf: sub = 8'h8a;
                        8'hd0: sub = 8'h70; 8'hd1: sub = 8'h3e; 8'hd2: sub = 8'hb5; 8'hd3: sub = 8'h66;
                        8'hd4: sub = 8'h48; 8'hd5: sub = 8'h03; 8'hd6: sub = 8'hf6; 8'hd7: sub = 8'h0e;
                        8'hd8: sub = 8'h61; 8'hd9: sub = 8'h35; 8'hda: sub = 8'h57; 8'hdb: sub = 8'hb9;
                        8'hdc: sub = 8'h86; 8'hdd: sub = 8'hc1; 8'hde: sub = 8'h1d; 8'hdf: sub = 8'h9e;
                        8'he0: sub = 8'he1; 8'he1: sub = 8'hf8; 8'he2: sub = 8'h98; 8'he3: sub = 8'h11;
                        8'he4: sub = 8'h69; 8'he5: sub = 8'hd9; 8'he6: sub = 8'h8e; 8'he7: sub = 8'h94;
                        8'he8: sub = 8'h9b; 8'he9: sub = 8'h1e; 8'hea: sub = 8'h87; 8'heb: sub = 8'he9;
                        8'hec: sub = 8'hce; 8'hed: sub = 8'h55; 8'hee: sub = 8'h28; 8'hef: sub = 8'hdf;
                        8'hf0: sub = 8'h8c; 8'hf1: sub = 8'ha1; 8'hf2: sub = 8'h89; 8'hf3: sub = 8'h0d;
                        8'hf4: sub = 8'hbf; 8'hf5: sub = 8'he6; 8'hf6: sub = 8'h42; 8'hf7: sub = 8'h68;
                        8'hf8: sub = 8'h41; 8'hf9: sub = 8'h99; 8'hfa: sub = 8'h2d; 8'hfb: sub = 8'h0f;
                        8'hfc: sub = 8'hb0; 8'hfd: sub = 8'h54; 8'hfe: sub = 8'hbb; 8'hff: sub = 8'h16;
                    endcase

        rot = rot >> 8;
        temp2 = {sub[7:0], temp2[31:8]};
        temp = temp << 8;
    

 
    if (word_counter == 4'he && rounds_counter ==4'h0) begin
        nextstate = EXPANSION_4;
    end 
    if (word_counter == 4'h8 && sub_roundcounter ==4'h2 && rounds_counter==4'h0) begin
        nextstate = RC_CON;
    end
    if (word_counter == 4'h4 && rounds_counter == 4'h1) begin
			 nextstate=RC_CON;
		end
	 if (word_counter == 4'ha && rounds_counter == 4'h1) begin
			 nextstate=EXPANSION_2;
		end


 end
 
	   
		RC_CON: begin
   		 case (rounds_counter)
        4'b0000: round_constant = {temp2[31:24] ^ 8'h01, temp2[23:0]};
        4'b0001: round_constant = {temp2[31:24] ^ 8'h02, temp2[23:0]};
        4'b0010: round_constant = {temp2[31:24] ^ 8'h04, temp2[23:0]};
        4'b0011: round_constant = {temp2[31:24] ^ 8'h08, temp2[23:0]};
        4'b0100: round_constant = {temp2[31:24] ^ 8'h10, temp2[23:0]};
        4'b0101: round_constant = {temp2[31:24] ^ 8'h20, temp2[23:0]};
        4'b0110: round_constant = {temp2[31:24] ^ 8'h40, temp2[23:0]};
       
    endcase

    if (sub_roundcounter == 4'h4) begin
        nextstate = EXPANSION_1;
    end else begin
        nextstate = EXPANSION_3;
    end
end

	EXPANSION_3: begin
		sub_roundcounter =sub_roundcounter+1;
    expansion3[31:0]  = expansion1[31:0] ^ round_constant;
    expansion3[63:32] = expansion1[63:32] ^ expansion3[31:0];
    expansion3[95:64] = expansion1[95:64] ^ expansion3[63:32];
    expansion3[127:96] = expansion1[127:96] ^ expansion3[95:64];
    
 
    rot = expansion3[127:96];
    sub_counter = 2'b00;
 
    
	   if (sub_roundcounter ==4'h3) begin
        round3_result = expansion3;
    end
 
		nextstate = SUB_BYTE;
		
end

	EXPANSION_4: begin
		    sub_roundcounter = sub_roundcounter + 1;

    expansion4[31:0]  = expansion2[31:0] ^ temp2;
    expansion4[63:32] = expansion2[63:32] ^ expansion4[31:0];
    expansion4[95:64] = expansion2[95:64] ^ expansion4[63:32];
    expansion4[127:96] = expansion2[127:96] ^ expansion4[95:64];

    if (rounds_counter == 1'b0) begin
        round4_result = expansion4;
    end


    if (sub_roundcounter == 4'h4) begin
        rounds_counter = rounds_counter + 1;
    end

    temp = expansion4[127:96];
    nextstate = ROT_BYTE;
end

	
        endcase
      end



// i've to implement a logiC THAT IF round counter is zero and sub_roundcounter =4'h2 and word_counter=4'h8 then next state would be RC_CON and if IF round counter is zero and sub_roundcounter =4'h3 and word counter ==4'hd next state == expansion 4;
// and IF round counter is 1 and sub_roundcounter =4'h4 and word_counter=4'h4 and then next state would be RC_CON and if IF round counter is 1 and sub_roundcounter =4'h5 and word counter ==4'ha next state == expansion 2;



endmodule

updatedkeyexpansion_tb.v
module updatedkeyexpansion_tb;

    // Testbench signals
    reg clk;
    reg rst;
    reg [255:0] key;
    wire [127:0] out_key;

    // Instantiate the keyexpansion module
    updatedkeyexpansion uut (
        .key(key),
        .clk(clk),
        .rst(rst),
        .out_key(out_key)
    );

    // Clock generation
    initial begin
        clk = 0;
        forever #5 clk = ~clk; // 10ns period
    end

    // Test sequence
    initial begin
        // Initialize inputs
        rst = 1;
        key = 256'h642423baa95efb4362d3f2ce993c0904150f258aa1fe796841d7b4429c9b5a30
;

        // Reset the system
        #10;
        rst = 0;
        #10;
        // rst = 1;

        // Apply test vectors
        #500; // Run simulation for some time

        // End simulation
        $finish;
        
    end

    // Waveform dump
    initial begin
        $dumpfile("updatedkeyexpansion.vcd");
        $dumpvars(0,updatedkeyexpansion_tb);
    end

 endmodule
// iverilog -o updatedkeyexpansion.out updatedkeyexpansion.v updatedkeyexpansion_tb.v
// vvp updatedkeyexpansion.out
// gtkwave updatedkeyexpansion.vcd

updatedkeyexpansion.vcd
$date
	Tue Jul 23 22:06:49 2024
$end
$version
	Icarus Verilog
$end
$timescale
	1s
$end
$scope module updatedkeyexpansion_tb $end
$var wire 128 ! out_key [127:0] $end
$var reg 1 " clk $end
$var reg 256 # key [255:0] $end
$var reg 1 $ rst $end
$scope module uut $end
$var wire 1 " clk $end
$var wire 256 % key [255:0] $end
$var wire 1 $ rst $end
$var parameter 4 & EXPANSION_1 $end
$var parameter 4 ' EXPANSION_2 $end
$var parameter 4 ( EXPANSION_3 $end
$var parameter 4 ) EXPANSION_4 $end
$var parameter 4 * IDLE $end
$var parameter 4 + RC_CON $end
$var parameter 4 , ROT_BYTE $end
$var parameter 4 - START $end
$var parameter 4 . SUB_BYTE $end
$var parameter 4 / XOR $end
$var reg 128 0 expansion1 [127:0] $end
$var reg 128 1 expansion2 [127:0] $end
$var reg 128 2 expansion3 [127:0] $end
$var reg 128 3 expansion4 [127:0] $end
$var reg 256 4 key_in [255:0] $end
$var reg 5 5 nextstate [4:0] $end
$var reg 128 6 out_key [127:0] $end
$var reg 32 7 rot [31:0] $end
$var reg 128 8 round1_result [127:0] $end
$var reg 128 9 round2_result [127:0] $end
$var reg 128 : round3_result [127:0] $end
$var reg 128 ; round4_result [127:0] $end
$var reg 128 < round5_result [127:0] $end
$var reg 32 = round_constant [31:0] $end
$var reg 4 > rounds_counter [3:0] $end
$var reg 2 ? second_subcounter [1:0] $end
$var reg 5 @ state [4:0] $end
$var reg 32 A sub [31:0] $end
$var reg 2 B sub_counter [1:0] $end
$var reg 4 C sub_roundcounter [3:0] $end
$var reg 32 D temp [31:0] $end
$var reg 32 E temp2 [31:0] $end
$var reg 4 F word_counter [3:0] $end
$upscope $end
$upscope $end
$enddefinitions $end
$comment Show the parameter values. $end
$dumpall
b1010 /
b1000 .
b10 -
b111 ,
b1001 +
b1 *
b110 )
b101 (
b100 '
b11 &
$end
#0
$dumpvars
bx F
bx E
bx D
b0 C
bx B
bx A
bx @
bx ?
b0 >
b0 =
bx <
bx ;
bx :
bx 9
bx 8
bx 7
bx 6
b0 5
bx 4
bx 3
bx 2
bx 1
bx 0
b110010000100100001000111011101010101001010111101111101101000011011000101101001111110010110011101001100100111100000010010000010000010101000011110010010110001010101000011111111001111001011010000100000111010111101101000100001010011100100110110101101000110000 %
1$
b110010000100100001000111011101010101001010111101111101101000011011000101101001111110010110011101001100100111100000010010000010000010101000011110010010110001010101000011111111001111001011010000100000111010111101101000100001010011100100110110101101000110000 #
0"
bx !
$end
#5
b10 5
b0 ?
b0 B
b0 F
b1 @
1"
#10
0"
0$
#15
b11 5
b110010000100100001000111011101010101001010111101111101101000011011000101101001111110010110011101001100100111100000010010000010000010101000011110010010110001010101000011111111001111001011010000100000111010111101101000100001010011100100110110101101000110000 4
b1 ?
b1 B
b1 F
b10 @
1"
#20
0"
#25
b100 5
b10101000011110010010110001010101000011111111001111001011010000100000111010111101101000100001010011100100110110101101000110000 8
b10101000011110010010110001010101000011111111001111001011010000100000111010111101101000100001010011100100110110101101000110000 0
b1 C
b10 ?
b10 B
b10 F
b11 @
1"
#30
0"
#35
b111 5
b1100100001001000010001110111010101010010101111011111011010000110110001011010011111100101100111010011001001111000000100100000100 9
b1100100001001000010001110111010 D
b1100100001001000010001110111010101010010101111011111011010000110110001011010011111100101100111010011001001111000000100100000100 1
b10 C
b11 ?
b11 B
b11 F
b100 @
1"
#40
0"
#45
b1000 5
b100100001000111011101001100100 7
b0 ?
b0 B
b100 F
b111 @
1"
#50
0"
#55
b100100001000111011101000000000 D
b1000011xxxxxxxxxxxxxxxxxxxxxxxx E
b1001000010001110111010 7
b1000011 A
b1 ?
b1 B
b101 F
b1000 @
1"
#60
0"
#65
b100011101110100000000000000000 D
b1111010001000011xxxxxxxxxxxxxxxx E
b10010000100011 7
b11110100 A
b10 ?
b10 B
b110 F
1"
#70
0"
#75
b10111010000000000000000000000000 D
b1001101111010001000011xxxxxxxx E
b100100 7
b100110 A
b11 ?
b11 B
b111 F
1"
#80
0"
#85
b1001 5
b0 D
b110110001001101111010001000011 E
b0 7
b110110 A
b0 ?
b0 B
b1000 F
1"
#90
0"
#95
b101 5
b110111001001101111010001000011 =
b1 ?
b1 B
b1001 F
b1001 @
1"
#100
0"
#105
b1000 5
b1011110100110110100011011010011010010111001010001100011010110011110101001101010000110100011000110101011101111011010111001110011 :
b1011110100110110100011011010011 7
b1011110100110110100011011010011010010111001010001100011010110011110101001101010000110100011000110101011101111011010111001110011 2
b11 C
b10 ?
b0 B
b1010 F
b101 @
1"
#110
0"
#115
b1100110001101100010011011110100 E
b10111101001101101000110 7
b1100110 A
b1 ?
b1 B
b1011 F
b1000 @
1"
#120
0"
#125
b1011010011001100011011000100110 E
b101111010011011 7
b1011010 A
b10 ?
b10 B
b1100 F
1"
#130
0"
#135
b10100010110100110011000110110 E
b1011110 7
b10100 A
b11 ?
b11 B
b1101 F
1"
#140
0"
#145
b110 5
b1011000000101000101101001100110 E
b0 7
b1011000 A
b0 ?
b0 B
b1110 F
1"
#150
0"
#155
b111 5
b1101110100000010111100101010101 D
b1 >
b1101110100000010111100101010101000010101010010101011010111011111010001111111011101000011010110011000001001010000101001101100010 ;
b1101110100000010111100101010101000010101010010101011010111011111010001111111011101000011010110011000001001010000101001101100010 3
b100 C
b1 ?
b1 B
b1111 F
b110 @
1"
#160
0"
#165
b1000 5
b10000001011110010101010101101110 7
b10 ?
b0 B
b0 F
b111 @
1"
#170
0"
#175
b10000001011110010101010100000000 D
b10011111010110000001010001011010 E
b100000010111100101010101 7
b10011111 A
b1 ?
b1 B
b1 F
b1000 @
1"
#180
0"
#185
b1111001010101010000000000000000 D
b11111100100111110101100000010100 E
b1000000101111001 7
b11111100 A
b10 ?
b10 B
b10 F
1"
#190
0"
#195
b1010101000000000000000000000000 D
b10110110111111001001111101011000 E
b10000001 7
b10110110 A
b11 ?
b11 B
b11 F
1"
#200
0"
#205
b1001 5
b0 D
b1100101101101111110010011111 E
b0 7
b1100 A
b0 ?
b0 B
b100 F
1"
#210
0"
#215
b11 5
b1110101101101111110010011111 =
b1 ?
b1 B
b101 F
b1001 @
1"
#220
0"
#225
b1000 5
b1011000011011100110110101010111 7
b1011000011011100110110101010111000001101111010100101011100001000100110101100001010010001101110110100111000010110101001011101100 <
b1011000011011100110110101010111000001101111010100101011100001000100110101100001010010001101110110100111000010110101001011101100 0
b101 C
b0 ?
b10 B
b110 F
b11 @
1"
#230
0"
#235
b1011011000011001011011011111100 E
b10110000110111001101101 7
b1011011 A
b11 ?
b11 B
b111 F
b1000 @
1"
#240
0"
#245
b111100010110110000110010110110 E
b101100001101110 7
b111100 A
b0 ?
b0 B
b1000 F
1"
#250
0"
#255
b10011111001111000101101100001100 E
b1011000 7
b10011111 A
b1 ?
b1 B
b1001 F
1"
#260
0"
#265
b100 5
b1101010100111110011110001011011 E
b0 7
b1101010 A
b10 ?
b10 B
b1010 F
1"
#270
0"
#275
b111 5
b110 C
b11 ?
b11 B
b1011 F
b100 @
1"
#280
0"
#285
b1000 5
b0 ?
b0 B
b1100 F
b111 @
1"
#290
0"
#295
b1100011011010101001111100111100 E
b1100011 A
b1 ?
b1 B
b1101 F
b1000 @
1"
#300
0"
#305
b1100011011000110110101010011111 E
b10 ?
b10 B
b1110 F
1"
#310
0"
#315
b1100011011000110110001101101010 E
b11 ?
b11 B
b1111 F
1"
#320
0"
#325
b1100011011000110110001101100011 E
b0 ?
b0 B
b0 F
1"
#330
0"
#335
b1 ?
b1 B
b1 F
1"
#340
0"
#345
b10 ?
b10 B
b10 F
1"
#350
0"
#355
b11 ?
b11 B
b11 F
1"
#360
0"
#365
b1001 5
b0 ?
b0 B
b100 F
1"
#370
0"
#375
b101 5
b1100001011000110110001101100011 =
b1 ?
b1 B
b101 F
b1001 @
1"
#380
0"
#385
b1000 5
b11010101100100100011111110000001 7
b11010101100100100011111110000001100011011111110001010010110101101000101100001001011110010101001011000110011010000011000110001111 2
b111 C
b10 ?
b0 B
b110 F
b101 @
1"
#390
0"
#395
b1100011000110110001101100011 E
b110101011001001000111111 7
b1100 A
b1 ?
b1 B
b111 F
b1000 @
1"
#400
0"
#405
b1110101000011000110001101100011 E
b1101010110010010 7
b1110101 A
b10 ?
b10 B
b1000 F
1"
#410
0"
#415
b1001111011101010000110001100011 E
b11010101 7
b1001111 A
b11 ?
b11 B
b1001 F
1"
#420
0"
#425
b100 5
b11010011110111010100001100 E
b0 7
b11 A
b0 ?
b0 B
b1010 F
1"
#430
0"
#435
b111 5
b1000 C
b1 ?
b1 B
b1011 F
b100 @
1"
#440
0"
#445
b1000 5
b10 ?
b0 B
b1100 F
b111 @
1"
#450
0"
#455
b1100011000000110100111101110101 E
b1100011 A
b1 ?
b1 B
b1101 F
b1000 @
1"
#460
0"
#465
b1100011011000110000001101001111 E
b10 ?
b10 B
b1110 F
1"
#470
0"
#475
b1100011011000110110001100000011 E
b11 ?
b11 B
b1111 F
1"
#480
0"
#485
b1100011011000110110001101100011 E
b0 ?
b0 B
b0 F
1"
#490
0"
#495
b1 ?
b1 B
b1 F
1"
#500
0"
#505
b10 ?
b10 B
b10 F
1"
#510
0"
#515
b11 ?
b11 B
b11 F
1"
