updatedkeyexpansion.v
module updatedkeyexpansion (
    input wire [255:0] key,
    input wire clk,
    input wire rst,
    output reg [127:0] out_key


);  reg [255:0] key_in,word;
    reg [127:0] expansion1,expansion2,expansion3,expansion4;
	reg expansion3_enable;
    reg [31:0] temp,temp2,rot,sub,round_constant,round_subword,word_1,word_2,word_3,word_4,word_5,word_6,word_7,word_8 =32'b0;
    reg [1:0] sub_counter,second_subcounter =2'b00;
    reg [4:0] state,nextstate =4'b0000;
    reg [3:0] word_counter,sub_roundcounter=4'b0000;
	reg [3:0] rounds_counter=4'b0000;

   localparam  IDLE=4'b0001 ;
   localparam  START=4'b0010 ;
   localparam  EXPANSION_1=4'b0011 ;
   localparam  EXPANSION_2=4'b0100 ;
   localparam  EXPANSION_3=4'b0101 ;
   localparam  EXPANSION_4=4'b0110 ;
   localparam  ROT_BYTE=4'b0111 ;
   localparam  SUB_BYTE=4'b1000 ;
   localparam  RC_CON=4'b1001 ;
   localparam  XOR=4'b1010 ;


always @(posedge clk) begin
        if (rst) begin
            state <= IDLE;
            word_counter <= 4'b0000;
            // secword_counter <= 4'b0000;
            sub_counter <= 2'b00;
        end 
		else begin
            state <= nextstate;
            word_counter <= word_counter + 1;
            sub_counter <= sub_counter + 1;
            // secword_counter <= secword_counter + 1;
        end
    end
      always @(*) begin
        
		second_subcounter=sub_counter;
     case (state)
        IDLE:begin
            nextstate=START;

        end
      START:begin
		
			key_in=key;
        
        nextstate=EXPANSION_1;

      end
      EXPANSION_1:begin
      if (rounds_counter==1'b0) begin
        expansion1=key_in[127:0];

      end
	   sub_roundcounter=sub_roundcounter+1;
      nextstate=EXPANSION_2;
      end
      EXPANSION_2:begin
        if(rounds_counter==1'b0)begin
          expansion2=key_in[256:128];
          temp =expansion2[127:96];
        end
           sub_roundcounter=sub_roundcounter+1;
     nextstate=ROT_BYTE;
      end
       ROT_BYTE:begin
       
       sub_counter =2'b00;
         rot ={temp[23:0],temp[31:24]};
        nextstate=SUB_BYTE;

        end
       SUB_BYTE:begin

         if (second_subcounter <= 2'b11)begin

        case (rot[7:0])
         8'h00: sub=8'h63;
	   8'h01: sub=8'h7c;
	   8'h02: sub=8'h77;
	   8'h03: sub=8'h7b;
	   8'h04: sub=8'hf2;
	   8'h05: sub=8'h6b;
	   8'h06: sub=8'h6f;
	   8'h07: sub=8'hc5;
	   8'h08: sub=8'h30;
	   8'h09: sub=8'h01;
	   8'h0a: sub=8'h67;
	   8'h0b: sub=8'h2b;
	   8'h0c: sub=8'hfe;
	   8'h0d: sub=8'hd7;
	   8'h0e: sub=8'hab;
	   8'h0f: sub=8'h76;
	   8'h10: sub=8'hca;
	   8'h11: sub=8'h82;
	   8'h12: sub=8'hc9;
	   8'h13: sub=8'h7d;
	   8'h14: sub=8'hfa;
	   8'h15: sub=8'h59;
	   8'h16: sub=8'h47;
	   8'h17: sub=8'hf0;
	   8'h18: sub=8'had;
	   8'h19: sub=8'hd4;
	   8'h1a: sub=8'ha2;
	   8'h1b: sub=8'haf;
	   8'h1c: sub=8'h9c;
	   8'h1d: sub=8'ha4;
	   8'h1e: sub=8'h72;
	   8'h1f: sub=8'hc0;
	   8'h20: sub=8'hb7;
	   8'h21: sub=8'hfd;
	   8'h22: sub=8'h93;
	   8'h23: sub=8'h26;
	   8'h24: sub=8'h36;
	   8'h25: sub=8'h3f;
	   8'h26: sub=8'hf7;
	   8'h27: sub=8'hcc;
	   8'h28: sub=8'h34;
	   8'h29: sub=8'ha5;
	   8'h2a: sub=8'he5;
	   8'h2b: sub=8'hf1;
	   8'h2c: sub=8'h71;
	   8'h2d: sub=8'hd8;
	   8'h2e: sub=8'h31;
	   8'h2f: sub=8'h15;
	   8'h30: sub=8'h04;
	   8'h31: sub=8'hc7;
	   8'h32: sub=8'h23;
	   8'h33: sub=8'hc3;
	   8'h34: sub=8'h18;
	   8'h35: sub=8'h96;
	   8'h36: sub=8'h05;
	   8'h37: sub=8'h9a;
	   8'h38: sub=8'h07;
	   8'h39: sub=8'h12;
	   8'h3a: sub=8'h80;
	   8'h3b: sub=8'he2;
	   8'h3c: sub=8'heb;
	   8'h3d: sub=8'h27;
	   8'h3e: sub=8'hb2;
	   8'h3f: sub=8'h75;
	   8'h40: sub=8'h09;
	   8'h41: sub=8'h83;
	   8'h42: sub=8'h2c;
	   8'h43: sub=8'h1a;
	   8'h44: sub=8'h1b;
	   8'h45: sub=8'h6e;
	   8'h46: sub=8'h5a;
	   8'h47: sub=8'ha0;
	   8'h48: sub=8'h52;
	   8'h49: sub=8'h3b;
	   8'h4a: sub=8'hd6;
	   8'h4b: sub=8'hb3;
	   8'h4c: sub=8'h29;
	   8'h4d: sub=8'he3;
	   8'h4e: sub=8'h2f;
	   8'h4f: sub=8'h84;
	   8'h50: sub=8'h53;
	   8'h51: sub=8'hd1;
	   8'h52: sub=8'h00;
	   8'h53: sub=8'hed;
	   8'h54: sub=8'h20;
	   8'h55: sub=8'hfc;
	   8'h56: sub=8'hb1;
	   8'h57: sub=8'h5b;
	   8'h58: sub=8'h6a;
	   8'h59: sub=8'hcb;
	   8'h5a: sub=8'hbe;
	   8'h5b: sub=8'h39;
	   8'h5c: sub=8'h4a;
	   8'h5d: sub=8'h4c;
	   8'h5e: sub=8'h58;
	   8'h5f: sub=8'hcf;
	   8'h60: sub=8'hd0;
	   8'h61: sub=8'hef;
	   8'h62: sub=8'haa;
	   8'h63: sub=8'hfb;
	   8'h64: sub=8'h43;
	   8'h65: sub=8'h4d;
       8'h66: sub=8'h33;
	   8'h67: sub=8'h85;
	   8'h68: sub=8'h45;
	   8'h69: sub=8'hf9;
	   8'h6a: sub=8'h02;
	   8'h6b: sub=8'h7f;
	   8'h6c: sub=8'h50;
	   8'h6d: sub=8'h3c;
	   8'h6e: sub=8'h9f;
	   8'h6f: sub=8'ha8;
	   8'h70: sub=8'h51;
	   8'h71: sub=8'ha3;
	   8'h72: sub=8'h40;
	   8'h73: sub=8'h8f;
	   8'h74: sub=8'h92;
	   8'h75: sub=8'h9d;
	   8'h76: sub=8'h38;
	   8'h77: sub=8'hf5;
	   8'h78: sub=8'hbc;
	   8'h79: sub=8'hb6;
	   8'h7a: sub=8'hda;
	   8'h7b: sub=8'h21;
	   8'h7c: sub=8'h10;
	   8'h7d: sub=8'hff;
	   8'h7e: sub=8'hf3;
	   8'h7f: sub=8'hd2;
	   8'h80: sub=8'hcd;
	   8'h81: sub=8'h0c;
	   8'h82: sub=8'h13;
	   8'h83: sub=8'hec;
	   8'h84: sub=8'h5f;
	   8'h85: sub=8'h97;
	   8'h86: sub=8'h44;
	   8'h87: sub=8'h17;
	   8'h88: sub=8'hc4;
	   8'h89: sub=8'ha7;
	   8'h8a: sub=8'h7e;
	   8'h8b: sub=8'h3d;
	   8'h8c: sub=8'h64;
	   8'h8d: sub=8'h5d;
	   8'h8e: sub=8'h19;
	   8'h8f: sub=8'h73;
	   8'h90: sub=8'h60;
	   8'h91: sub=8'h81;
	   8'h92: sub=8'h4f;
	   8'h93: sub=8'hdc;
	   8'h94: sub=8'h22;
	   8'h95: sub=8'h2a;
	   8'h96: sub=8'h90;
	   8'h97: sub=8'h88;
	   8'h98: sub=8'h46;
	   8'h99: sub=8'hee;
	   8'h9a: sub=8'hb8;
	   8'h9b: sub=8'h14;
	   8'h9c: sub=8'hde;
	   8'h9d: sub=8'h5e;
	   8'h9e: sub=8'h0b;
	   8'h9f: sub=8'hdb;
	   8'ha0: sub=8'he0;
	   8'ha1: sub=8'h32;
	   8'ha2: sub=8'h3a;
	   8'ha3: sub=8'h0a;
	   8'ha4: sub=8'h49;
	   8'ha5: sub=8'h06;
	   8'ha6: sub=8'h24;
	   8'ha7: sub=8'h5c;
	   8'ha8: sub=8'hc2;
	   8'ha9: sub=8'hd3;
	   8'haa: sub=8'hac;
	   8'hab: sub=8'h62;
	   8'hac: sub=8'h91;
	   8'had: sub=8'h95;
	   8'hae: sub=8'he4;
	   8'haf: sub=8'h79;
	   8'hb0: sub=8'he7;
	   8'hb1: sub=8'hc8;
	   8'hb2: sub=8'h37;
	   8'hb3: sub=8'h6d;
	   8'hb4: sub=8'h8d;
	   8'hb5: sub=8'hd5;
	   8'hb6: sub=8'h4e;
	   8'hb7: sub=8'ha9;
	   8'hb8: sub=8'h6c;
	   8'hb9: sub=8'h56;
	   8'hba: sub=8'hf4;
	   8'hbb: sub=8'hea;
	   8'hbc: sub=8'h65;
	   8'hbd: sub=8'h7a;
	   8'hbe: sub=8'hae;
	   8'hbf: sub=8'h08;
	   8'hc0: sub=8'hba;
	   8'hc1: sub=8'h78;
	   8'hc2: sub=8'h25;
	   8'hc3: sub=8'h2e;
	   8'hc4: sub=8'h1c;
	   8'hc5: sub=8'ha6;
	   8'hc6: sub=8'hb4;
	   8'hc7: sub=8'hc6;
	   8'hc8: sub=8'he8;
	   8'hc9: sub=8'hdd;
	   8'hca: sub=8'h74;
	   8'hcb: sub=8'h1f;
	   8'hcc: sub=8'h4b;
	   8'hcd: sub=8'hbd;
	   8'hce: sub=8'h8b;
	   8'hcf: sub=8'h8a;
	   8'hd0: sub=8'h70;
	   8'hd1: sub=8'h3e;
	   8'hd2: sub=8'hb5;
	   8'hd3: sub=8'h66;
	   8'hd4: sub=8'h48;
	   8'hd5: sub=8'h03;
	   8'hd6: sub=8'hf6;
	   8'hd7: sub=8'h0e;
	   8'hd8: sub=8'h61;
	   8'hd9: sub=8'h35;
	   8'hda: sub=8'h57;
	   8'hdb: sub=8'hb9;
	   8'hdc: sub=8'h86;
	   8'hdd: sub=8'hc1;
	   8'hde: sub=8'h1d;
	   8'hdf: sub=8'h9e;
	   8'he0: sub=8'he1;
	   8'he1: sub=8'hf8;
	   8'he2: sub=8'h98;
	   8'he3: sub=8'h11;
	   8'he4: sub=8'h69;
	   8'he5: sub=8'hd9;
	   8'he6: sub=8'h8e;
	   8'he7: sub=8'h94;
	   8'he8: sub=8'h9b;
	   8'he9: sub=8'h1e;
	   8'hea: sub=8'h87;
	   8'heb: sub=8'he9;
	   8'hec: sub=8'hce;
	   8'hed: sub=8'h55;
	   8'hee: sub=8'h28;
	   8'hef: sub=8'hdf;
	   8'hf0: sub=8'h8c;
	   8'hf1: sub=8'ha1;
	   8'hf2: sub=8'h89;
	   8'hf3: sub=8'h0d;
	   8'hf4: sub=8'hbf;
	   8'hf5: sub=8'he6;
	   8'hf6: sub=8'h42;
	   8'hf7: sub=8'h68;
	   8'hf8: sub=8'h41;
	   8'hf9: sub=8'h99;
	   8'hfa: sub=8'h2d;
	   8'hfb: sub=8'h0f;
	   8'hfc: sub=8'hb0;
	   8'hfd: sub=8'h54;
	   8'hfe: sub=8'hbb;
	   8'hff: sub=8'h16;
        endcase
        rot =rot>>8;
		temp2={sub[7:0],temp2[31:8]};
		temp =temp<<8;
		 end
    		
			if (word_counter==4'he) begin
				nextstate=EXPANSION_4;
			end
		 else begin
		if(word_counter==4'h8 ||secon)begin	
	      nextstate=RC_CON;
		end
		end
	   end
	RC_CON:begin
		
		 round_constant = {temp2[31:24] ^ 8'h01, temp2[23:0]};

      nextstate=EXPANSION_3;
	end
	EXPANSION_3:begin
	expansion3[31:0]=expansion1[31:0]^round_constant;
	expansion3[63:32]=expansion1[63:32]^expansion3[31:0];
	expansion3[95:64]=expansion1[95:64]^expansion3[63:32];
	expansion3[127:96]=expansion1[127:96]^expansion3[95:64];
	
	sub_roundcounter=sub_roundcounter+1;
	rot=expansion3[127:96];
	//  expansion3_enable=1'b1;
	sub_counter=2'b00;
	second_subcounter=sub_counter;
	if(second_subcounter <= 2'b11)begin
	
	expansion3_enable=1'b0;
	end
	nextstate=SUB_BYTE;
	end
	EXPANSION_4:begin
		expansion3_enable=1'b1;
		expansion4[31:0]=expansion2[31:0]^temp2;
	expansion4[63:32]=expansion2[63:32]^expansion4[31:0];
	expansion4[95:64]=expansion2[95:64]^expansion4[63:32];
	expansion4[127:96]=expansion2[127:96]^expansion4[95:64];
	sub_roundcounter=sub_roundcounter+1;
	if(sub_roundcounter==4'd4) begin
		rounds_counter=rounds_counter+1;
	end
	temp=expansion4[127:96];
	nextstate=ROT_BYTE;
	end
	
        endcase
      end
























endmodule

updatedkeyexpansion_tb.v
module updatedkeyexpansion_tb;

    // Testbench signals
    reg clk;
    reg rst;
    reg [255:0] key;
    wire [127:0] out_key;

    // Instantiate the keyexpansion module
    updatedkeyexpansion uut (
        .key(key),
        .clk(clk),
        .rst(rst),
        .out_key(out_key)
    );

    // Clock generation
    initial begin
        clk = 0;
        forever #5 clk = ~clk; // 10ns period
    end

    // Test sequence
    initial begin
        // Initialize inputs
        rst = 1;
        key = 256'h642423baa95efb4362d3f2ce993c0904150f258aa1fe796841d7b4429c9b5a30
;

        // Reset the system
        #10;
        rst = 0;
        #10;
        // rst = 1;

        // Apply test vectors
        #260; // Run simulation for some time

        // End simulation
        $finish;
        
    end

    // Waveform dump
    initial begin
        $dumpfile("updatedkeyexpansion.vcd");
        $dumpvars(0,updatedkeyexpansion_tb);
    end

 endmodule
// iverilog -o updatedkeyexpansion.out updatedkeyexpansion.v updatedkeyexpansion_tb.v
// vvp updatedkeyexpansion.out
// gtkwave updatedkeyexpansion.vcd

updatedkeyexpansion.vcd
$date
	Mon Jul 22 15:00:45 2024
$end
$version
	Icarus Verilog
$end
$timescale
	1s
$end
$scope module updatedkeyexpansion_tb $end
$var wire 128 ! out_key [127:0] $end
$var reg 1 " clk $end
$var reg 256 # key [255:0] $end
$var reg 1 $ rst $end
$scope module uut $end
$var wire 1 " clk $end
$var wire 256 % key [255:0] $end
$var wire 1 $ rst $end
$var parameter 4 & EXPANSION_1 $end
$var parameter 4 ' EXPANSION_2 $end
$var parameter 4 ( EXPANSION_3 $end
$var parameter 4 ) EXPANSION_4 $end
$var parameter 4 * IDLE $end
$var parameter 4 + RC_CON $end
$var parameter 4 , ROT_BYTE $end
$var parameter 4 - START $end
$var parameter 4 . SUB_BYTE $end
$var parameter 4 / XOR $end
$var reg 128 0 expansion1 [127:0] $end
$var reg 128 1 expansion2 [127:0] $end
$var reg 128 2 expansion3 [127:0] $end
$var reg 1 3 expansion3_enable $end
$var reg 128 4 expansion4 [127:0] $end
$var reg 256 5 key_in [255:0] $end
$var reg 5 6 nextstate [4:0] $end
$var reg 128 7 out_key [127:0] $end
$var reg 32 8 rot [31:0] $end
$var reg 32 9 round_constant [31:0] $end
$var reg 4 : rounds_counter [3:0] $end
$var reg 2 ; second_subcounter [1:0] $end
$var reg 5 < state [4:0] $end
$var reg 32 = sub [31:0] $end
$var reg 2 > sub_counter [1:0] $end
$var reg 4 ? sub_roundcounter [3:0] $end
$var reg 32 @ temp [31:0] $end
$var reg 32 A temp2 [31:0] $end
$var reg 32 B word_8 [31:0] $end
$var reg 4 C word_counter [3:0] $end
$upscope $end
$upscope $end
$enddefinitions $end
$comment Show the parameter values. $end
$dumpall
b1010 /
b1000 .
b10 -
b111 ,
b1001 +
b1 *
b110 )
b101 (
b100 '
b11 &
$end
#0
$dumpvars
bx C
b0 B
bx A
bx @
b0 ?
bx >
bx =
bx <
bx ;
b0 :
bx 9
bx 8
bx 7
b0 6
bx 5
bx 4
x3
bx 2
bx 1
bx 0
b110010000100100001000111011101010101001010111101111101101000011011000101101001111110010110011101001100100111100000010010000010000010101000011110010010110001010101000011111111001111001011010000100000111010111101101000100001010011100100110110101101000110000 %
1$
b110010000100100001000111011101010101001010111101111101101000011011000101101001111110010110011101001100100111100000010010000010000010101000011110010010110001010101000011111111001111001011010000100000111010111101101000100001010011100100110110101101000110000 #
0"
bx !
$end
#5
b10 6
b0 ;
b0 >
b0 C
b1 <
1"
#10
0"
0$
#15
b11 6
b110010000100100001000111011101010101001010111101111101101000011011000101101001111110010110011101001100100111100000010010000010000010101000011110010010110001010101000011111111001111001011010000100000111010111101101000100001010011100100110110101101000110000 5
b1 ;
b1 >
b1 C
b10 <
1"
#20
0"
#25
b100 6
b1 ?
b10101000011110010010110001010101000011111111001111001011010000100000111010111101101000100001010011100100110110101101000110000 0
b10 ;
b10 >
b10 C
b11 <
1"
#30
0"
#35
b111 6
b10 ?
b1100100001001000010001110111010 @
b1100100001001000010001110111010101010010101111011111011010000110110001011010011111100101100111010011001001111000000100100000100 1
b11 ;
b11 >
b11 C
b100 <
1"
#40
0"
#45
b1000 6
b100100001000111011101001100100 8
b0 ;
b0 >
b100 C
b111 <
1"
#50
0"
#55
b100100001000111011101000000000 @
b1000011xxxxxxxxxxxxxxxxxxxxxxxx A
b1001000010001110111010 8
b1000011 =
b1 ;
b1 >
b101 C
b1000 <
1"
#60
0"
#65
b100011101110100000000000000000 @
b1111010001000011xxxxxxxxxxxxxxxx A
b10010000100011 8
b11110100 =
b10 ;
b10 >
b110 C
1"
#70
0"
#75
b10111010000000000000000000000000 @
b1001101111010001000011xxxxxxxx A
b100100 8
b100110 =
b11 ;
b11 >
b111 C
1"
#80
0"
#85
b1001 6
b0 @
b110110001001101111010001000011 A
b0 8
b110110 =
b0 ;
b0 >
b1000 C
1"
#90
0"
#95
b101 6
b110111001001101111010001000011 9
b1 ;
b1 >
b1001 C
b1001 <
1"
#100
0"
#105
b1000 6
03
b1011110100110110100011011010011 8
b11 ?
b1011110100110110100011011010011010010111001010001100011010110011110101001101010000110100011000110101011101111011010111001110011 2
b0 ;
b0 >
b1010 C
b101 <
1"
#110
0"
#115
b1100110001101100010011011110100 A
b10111101001101101000110 8
b1100110 =
b1 ;
b1 >
b1011 C
b1000 <
1"
#120
0"
#125
b1011010011001100011011000100110 A
b101111010011011 8
b1011010 =
b10 ;
b10 >
b1100 C
1"
#130
0"
#135
b10100010110100110011000110110 A
b1011110 8
b10100 =
b11 ;
b11 >
b1101 C
1"
#140
0"
#145
b110 6
b1011000000101000101101001100110 A
b0 8
b1011000 =
b0 ;
b0 >
b1110 C
1"
#150
0"
#155
b111 6
b1101110100000010111100101010101 @
b1 :
b100 ?
b1101110100000010111100101010101000010101010010101011010111011111010001111111011101000011010110011000001001010000101001101100010 4
13
b1 ;
b1 >
b1111 C
b110 <
1"
#160
0"
#165
b1000 6
b10000001011110010101010101101110 8
b10 ;
b0 >
b0 C
b111 <
1"
#170
0"
#175
b10000001011110010101010100000000 @
b10011111010110000001010001011010 A
b100000010111100101010101 8
b10011111 =
b1 ;
b1 >
b1 C
b1000 <
1"
#180
0"
#185
b1111001010101010000000000000000 @
b11111100100111110101100000010100 A
b1000000101111001 8
b11111100 =
b10 ;
b10 >
b10 C
1"
#190
0"
#195
b1010101000000000000000000000000 @
b10110110111111001001111101011000 A
b10000001 8
b10110110 =
b11 ;
b11 >
b11 C
1"
#200
0"
#205
b0 @
b1100101101101111110010011111 A
b0 8
b1100 =
b0 ;
b0 >
b100 C
1"
#210
0"
#215
b1100011000011001011011011111100 A
b1100011 =
b1 ;
b1 >
b101 C
1"
#220
0"
#225
b1100011011000110000110010110110 A
b10 ;
b10 >
b110 C
1"
#230
0"
#235
b1100011011000110110001100001100 A
b11 ;
b11 >
b111 C
1"
#240
0"
#245
b1001 6
b1100011011000110110001101100011 A
b0 ;
b0 >
b1000 C
1"
#250
0"
#255
b101 6
b1100010011000110110001101100011 9
b1 ;
b1 >
b1001 C
b1001 <
1"
#260
0"
#265
b1000 6
03
b1011110111101101000111110011 8
b101 ?
b1011110111101101000111110011000111101101000111110100011110011011111100101111100011010001000111111110111110000011100101010011 2
b0 ;
b0 >
b1010 C
b101 <
1"
#270
0"
#275
b1101011000110110001101100011 A
b10111101111011010001 8
b1101 =
b1 ;
b1 >
b1011 C
b1000 <
1"
