updatedkeyexpansion.v
module updatedkeyexpansion (
    input wire [255:0] key,
    input wire clk,
    input wire rst,
    output reg [127:0] out_key


);  reg [255:0] key_in,word;
    reg [127:0] expansion1,expansion2,expansion3,expansion4,round1_result,round2_result,round3_result,round4_result,round5_result,round6_result,round7_result,round8_result,round9_result,round10_result,round11_result,round12_result,round13_result,round14_result,round15_result;
	reg expansion3_enable,expansion4_enable;
    reg [31:0] temp,temp2,rot,sub,round_constant=32'b0;
    reg [1:0] sub_counter,second_subcounter =2'b00;
    reg [4:0] state,nextstate =4'b0000;
    reg [3:0] word_counter,sub_roundcounter=4'b0000;
	reg [3:0] rounds_counter=4'b0000;

   localparam  IDLE=4'b0001 ;
   localparam  START=4'b0010 ;
   localparam  EXPANSION_1=4'b0011 ;
   localparam  EXPANSION_2=4'b0100 ;
   localparam  EXPANSION_3=4'b0101 ;
   localparam  EXPANSION_4=4'b0110 ;
   localparam  ROT_BYTE=4'b0111 ;
   localparam  SUB_BYTE=4'b1000 ;
   localparam  RC_CON=4'b1001 ;
   localparam  XOR=4'b1010 ;
   localparam  DONE=4'b1011 ;


always @(posedge clk) begin
        if (rst) begin
            state <= IDLE;
            word_counter <= 4'b0000;
            
            sub_counter <= 2'b00;
        end 
		else begin
            state <= nextstate;
            word_counter <= word_counter + 1;
            sub_counter <= sub_counter + 1;
           
        end
    end
always @(*) begin
    second_subcounter = sub_counter;
    case (state)
        IDLE: begin
            nextstate = START;
        end

        START: begin
            key_in = key;
            nextstate = EXPANSION_1;
        end

        EXPANSION_1: begin
			sub_roundcounter = sub_roundcounter + 1;
            if (rounds_counter == 1'h0) begin
                expansion1 = key_in[127:0];
                round1_result = expansion1;
				nextstate=EXPANSION_2;
            end 
		
			else begin
			if(sub_roundcounter == 4'h5) begin
                expansion1[31:0]   = round3_result[31:0] ^ temp2;
                expansion1[63:32]  = round3_result[63:32] ^ expansion1[31:0];
                expansion1[95:64]  = round3_result[95:64] ^ expansion1[63:32];
                expansion1[127:96] = round3_result[127:96] ^ expansion1[95:64];
				round5_result=expansion1;
				rot = round5_result[127:96];
                second_subcounter=2'h0;
				nextstate =SUB_BYTE;
            end
             if(sub_roundcounter == 4'h9) begin
                 expansion1[31:0]   = round7_result[31:0] ^ temp2;
                 expansion1[63:32]  = round7_result[63:32] ^ expansion1[31:0];
                 expansion1[95:64]  = round7_result[95:64] ^ expansion1[63:32];
                 expansion1[127:96] = round7_result[127:96] ^ expansion1[95:64];
				round9_result=expansion1;
				rot = round9_result[127:96];
                second_subcounter=2'h0;
				nextstate =SUB_BYTE;
            end
            if(sub_roundcounter == 4'hD) begin
                 expansion1[31:0]   = round11_result[31:0] ^ temp2;
                 expansion1[63:32]  = round11_result[63:32] ^ expansion1[31:0];
                 expansion1[95:64]  = round11_result[95:64] ^ expansion1[63:32];
                 expansion1[127:96] = round11_result[127:96] ^ expansion1[95:64];
				round13_result=expansion1;
				rot = round13_result[127:96];
                second_subcounter=2'h0;
				nextstate =SUB_BYTE;
            end
			end
		end
        
		EXPANSION_2: begin 	
			sub_roundcounter=sub_roundcounter+1;
            if (sub_roundcounter == 4'h2) begin
                expansion2 = key_in[256:128];
                temp = expansion2[127:96];
                round2_result = expansion2;
            end

            if(sub_roundcounter==4'h6)begin

                 expansion2[31:0]   = round4_result[31:0] ^ temp2;
                expansion2[63:32]  = round4_result[63:32] ^ expansion2[31:0];
                expansion2[95:64]  = round4_result[95:64] ^ expansion2[63:32];
                expansion2[127:96] = round4_result[127:96] ^ expansion2[95:64];
				round6_result=expansion2;
                temp=round6_result[127:96];
            end
            if(sub_roundcounter==4'hA)begin

                 expansion2[31:0]   = round8_result[31:0] ^ temp2;
                expansion2[63:32]  = round8_result[63:32] ^ expansion2[31:0];
                expansion2[95:64]  = round8_result[95:64] ^ expansion2[63:32];
                expansion2[127:96] = round8_result[127:96] ^ expansion2[95:64];
				round10_result=expansion2;
                temp=round10_result[127:96];
            end
              if(sub_roundcounter==4'hE)begin

                 expansion2[31:0]   = round12_result[31:0] ^ temp2;
                expansion2[63:32]  = round12_result[63:32] ^ expansion2[31:0];
                expansion2[95:64]  = round12_result[95:64] ^ expansion2[63:32];
                expansion2[127:96] = round12_result[127:96] ^ expansion2[95:64];
				round14_result=expansion2;
                temp=round14_result[127:96];
            end

            nextstate = ROT_BYTE;

        end

        ROT_BYTE: begin
            sub_counter = 2'b00;
            rot = {temp[23:0], temp[31:24]};
            nextstate = SUB_BYTE;
        end
       SUB_BYTE: begin
                
                 
                    case (rot[7:0])
                        8'h00: sub = 8'h63; 8'h01: sub = 8'h7c; 8'h02: sub = 8'h77; 8'h03: sub = 8'h7b;
                        8'h04: sub = 8'hf2; 8'h05: sub = 8'h6b; 8'h06: sub = 8'h6f; 8'h07: sub = 8'hc5;
                        8'h08: sub = 8'h30; 8'h09: sub = 8'h01; 8'h0a: sub = 8'h67; 8'h0b: sub = 8'h2b;
                        8'h0c: sub = 8'hfe; 8'h0d: sub = 8'hd7; 8'h0e: sub = 8'hab; 8'h0f: sub = 8'h76;
                        8'h10: sub = 8'hca; 8'h11: sub = 8'h82; 8'h12: sub = 8'hc9; 8'h13: sub = 8'h7d;
                        8'h14: sub = 8'hfa; 8'h15: sub = 8'h59; 8'h16: sub = 8'h47; 8'h17: sub = 8'hf0;
                        8'h18: sub = 8'had; 8'h19: sub = 8'hd4; 8'h1a: sub = 8'ha2; 8'h1b: sub = 8'haf;
                        8'h1c: sub = 8'h9c; 8'h1d: sub = 8'ha4; 8'h1e: sub = 8'h72; 8'h1f: sub = 8'hc0;
                        8'h20: sub = 8'hb7; 8'h21: sub = 8'hfd; 8'h22: sub = 8'h93; 8'h23: sub = 8'h26;
                        8'h24: sub = 8'h36; 8'h25: sub = 8'h3f; 8'h26: sub = 8'hf7; 8'h27: sub = 8'hcc;
                        8'h28: sub = 8'h34; 8'h29: sub = 8'ha5; 8'h2a: sub = 8'he5; 8'h2b: sub = 8'hf1;
                        8'h2c: sub = 8'h71; 8'h2d: sub = 8'hd8; 8'h2e: sub = 8'h31; 8'h2f: sub = 8'h15;
                        8'h30: sub = 8'h04; 8'h31: sub = 8'hc7; 8'h32: sub = 8'h23; 8'h33: sub = 8'hc3;
                        8'h34: sub = 8'h18; 8'h35: sub = 8'h96; 8'h36: sub = 8'h05; 8'h37: sub = 8'h9a;
                        8'h38: sub = 8'h07; 8'h39: sub = 8'h12; 8'h3a: sub = 8'h80; 8'h3b: sub = 8'he2;
                        8'h3c: sub = 8'heb; 8'h3d: sub = 8'h27; 8'h3e: sub = 8'hb2; 8'h3f: sub = 8'h75;
                        8'h40: sub = 8'h09; 8'h41: sub = 8'h83; 8'h42: sub = 8'h2c; 8'h43: sub = 8'h1a;
                        8'h44: sub = 8'h1b; 8'h45: sub = 8'h6e; 8'h46: sub = 8'h5a; 8'h47: sub = 8'ha0;
                        8'h48: sub = 8'h52; 8'h49: sub = 8'h3b; 8'h4a: sub = 8'hd6; 8'h4b: sub = 8'hb3;
                        8'h4c: sub = 8'h29; 8'h4d: sub = 8'he3; 8'h4e: sub = 8'h2f; 8'h4f: sub = 8'h84;
                        8'h50: sub = 8'h53; 8'h51: sub = 8'hd1; 8'h52: sub = 8'h00; 8'h53: sub = 8'hed;
                        8'h54: sub = 8'h20; 8'h55: sub = 8'hfc; 8'h56: sub = 8'hb1; 8'h57: sub = 8'h5b;
                        8'h58: sub = 8'h6a; 8'h59: sub = 8'hcb; 8'h5a: sub = 8'hbe; 8'h5b: sub = 8'h39;
                        8'h5c: sub = 8'h4a; 8'h5d: sub = 8'h4c; 8'h5e: sub = 8'h58; 8'h5f: sub = 8'hcf;
                        8'h60: sub = 8'hd0; 8'h61: sub = 8'hef; 8'h62: sub = 8'haa; 8'h63: sub = 8'hfb;
                        8'h64: sub = 8'h43; 8'h65: sub = 8'h4d; 8'h66: sub = 8'h33; 8'h67: sub = 8'h85;
                        8'h68: sub = 8'h45; 8'h69: sub = 8'hf9; 8'h6a: sub = 8'h02; 8'h6b: sub = 8'h7f;
                        8'h6c: sub = 8'h50; 8'h6d: sub = 8'h3c; 8'h6e: sub = 8'h9f; 8'h6f: sub = 8'ha8;
                        8'h70: sub = 8'h51; 8'h71: sub = 8'ha3; 8'h72: sub = 8'h40; 8'h73: sub = 8'h8f;
                        8'h74: sub = 8'h92; 8'h75: sub = 8'h9d; 8'h76: sub = 8'h38; 8'h77: sub = 8'hf5;
                        8'h78: sub = 8'hbc; 8'h79: sub = 8'hb6; 8'h7a: sub = 8'hda; 8'h7b: sub = 8'h21;
                        8'h7c: sub = 8'h10; 8'h7d: sub = 8'hff; 8'h7e: sub = 8'hf3; 8'h7f: sub = 8'hd2;
                        8'h80: sub = 8'hcd; 8'h81: sub = 8'h0c; 8'h82: sub = 8'h13; 8'h83: sub = 8'hec;
                        8'h84: sub = 8'h5f; 8'h85: sub = 8'h97; 8'h86: sub = 8'h44; 8'h87: sub = 8'h17;
                        8'h88: sub = 8'hc4; 8'h89: sub = 8'ha7; 8'h8a: sub = 8'h7e; 8'h8b: sub = 8'h3d;
                        8'h8c: sub = 8'h64; 8'h8d: sub = 8'h5d; 8'h8e: sub = 8'h19; 8'h8f: sub = 8'h73;
                        8'h90: sub = 8'h60; 8'h91: sub = 8'h81; 8'h92: sub = 8'h4f; 8'h93: sub = 8'hdc;
                        8'h94: sub = 8'h22; 8'h95: sub = 8'h2a; 8'h96: sub = 8'h90; 8'h97: sub = 8'h88;
                        8'h98: sub = 8'h46; 8'h99: sub = 8'hee; 8'h9a: sub = 8'hb8; 8'h9b: sub = 8'h14;
                        8'h9c: sub = 8'hde; 8'h9d: sub = 8'h5e; 8'h9e: sub = 8'h0b; 8'h9f: sub = 8'hdb;
                        8'ha0: sub = 8'he0; 8'ha1: sub = 8'h32; 8'ha2: sub = 8'h3a; 8'ha3: sub = 8'h0a;
                        8'ha4: sub = 8'h49; 8'ha5: sub = 8'h06; 8'ha6: sub = 8'h24; 8'ha7: sub = 8'h5c;
                        8'ha8: sub = 8'hc2; 8'ha9: sub = 8'hd3; 8'haa: sub = 8'hac; 8'hab: sub = 8'h62;
                        8'hac: sub = 8'h91; 8'had: sub = 8'h95; 8'hae: sub = 8'he4; 8'haf: sub = 8'h79;
                        8'hb0: sub = 8'he7; 8'hb1: sub = 8'hc8; 8'hb2: sub = 8'h37; 8'hb3: sub = 8'h6d;
                        8'hb4: sub = 8'h8d; 8'hb5: sub = 8'hd5; 8'hb6: sub = 8'h4e; 8'hb7: sub = 8'ha9;
                        8'hb8: sub = 8'h6c; 8'hb9: sub = 8'h56; 8'hba: sub = 8'hf4; 8'hbb: sub = 8'hea;
                        8'hbc: sub = 8'h65; 8'hbd: sub = 8'h7a; 8'hbe: sub = 8'hae; 8'hbf: sub = 8'h08;
                        8'hc0: sub = 8'hba; 8'hc1: sub = 8'h78; 8'hc2: sub = 8'h25; 8'hc3: sub = 8'h2e;
                        8'hc4: sub = 8'h1c; 8'hc5: sub = 8'ha6; 8'hc6: sub = 8'hb4; 8'hc7: sub = 8'hc6;
                        8'hc8: sub = 8'he8; 8'hc9: sub = 8'hdd; 8'hca: sub = 8'h74; 8'hcb: sub = 8'h1f;
                        8'hcc: sub = 8'h4b; 8'hcd: sub = 8'hbd; 8'hce: sub = 8'h8b; 8'hcf: sub = 8'h8a;
                        8'hd0: sub = 8'h70; 8'hd1: sub = 8'h3e; 8'hd2: sub = 8'hb5; 8'hd3: sub = 8'h66;
                        8'hd4: sub = 8'h48; 8'hd5: sub = 8'h03; 8'hd6: sub = 8'hf6; 8'hd7: sub = 8'h0e;
                        8'hd8: sub = 8'h61; 8'hd9: sub = 8'h35; 8'hda: sub = 8'h57; 8'hdb: sub = 8'hb9;
                        8'hdc: sub = 8'h86; 8'hdd: sub = 8'hc1; 8'hde: sub = 8'h1d; 8'hdf: sub = 8'h9e;
                        8'he0: sub = 8'he1; 8'he1: sub = 8'hf8; 8'he2: sub = 8'h98; 8'he3: sub = 8'h11;
                        8'he4: sub = 8'h69; 8'he5: sub = 8'hd9; 8'he6: sub = 8'h8e; 8'he7: sub = 8'h94;
                        8'he8: sub = 8'h9b; 8'he9: sub = 8'h1e; 8'hea: sub = 8'h87; 8'heb: sub = 8'he9;
                        8'hec: sub = 8'hce; 8'hed: sub = 8'h55; 8'hee: sub = 8'h28; 8'hef: sub = 8'hdf;
                        8'hf0: sub = 8'h8c; 8'hf1: sub = 8'ha1; 8'hf2: sub = 8'h89; 8'hf3: sub = 8'h0d;
                        8'hf4: sub = 8'hbf; 8'hf5: sub = 8'he6; 8'hf6: sub = 8'h42; 8'hf7: sub = 8'h68;
                        8'hf8: sub = 8'h41; 8'hf9: sub = 8'h99; 8'hfa: sub = 8'h2d; 8'hfb: sub = 8'h0f;
                        8'hfc: sub = 8'hb0; 8'hfd: sub = 8'h54; 8'hfe: sub = 8'hbb; 8'hff: sub = 8'h16;
                    endcase

        rot = rot >> 8;
        temp2 = {sub[7:0], temp2[31:8]};
        temp = temp << 8;
    

 
    if (word_counter == 4'he && rounds_counter ==4'h0) begin
        nextstate = EXPANSION_4;
    end 
    if (word_counter == 4'h8 && sub_roundcounter ==4'h2 && rounds_counter==4'h0) begin
        nextstate = RC_CON;
    end
    if (word_counter == 4'h4 && rounds_counter == 4'h1 &&sub_roundcounter==4'h4) begin
			 nextstate=RC_CON;
		end
	 if (word_counter == 4'ha && rounds_counter == 4'h1) begin
			 nextstate=EXPANSION_2;
		end
		
	 if (word_counter == 4'h0 && rounds_counter == 4'h1) begin
			 nextstate=RC_CON;
		end
    if(word_counter ==4'h6 && rounds_counter ==4'h1 && sub_roundcounter==4'h7)begin
            nextstate=EXPANSION_4;
 end
    if(word_counter ==4'hc && rounds_counter ==4'h2 && sub_roundcounter==4'h8)begin
            nextstate=EXPANSION_1;
 end
    if(word_counter ==4'h1 && rounds_counter ==4'h2 && sub_roundcounter==4'h9)begin
            nextstate=EXPANSION_2;
 end
 
    if(word_counter ==4'h7 && rounds_counter ==4'h2 && sub_roundcounter==4'ha)begin
            nextstate=RC_CON;
 end
    if(word_counter ==4'hD && rounds_counter ==4'h2 && sub_roundcounter==4'hB)begin
            nextstate=EXPANSION_4;
 end
 if(word_counter ==4'h3 && rounds_counter ==4'h3 && sub_roundcounter==4'hC)begin
            nextstate=EXPANSION_1;
 end
 if(word_counter ==4'h3 && rounds_counter ==4'h3 && sub_roundcounter==4'hC)begin
            nextstate=RC_CON;
 end
 if(word_counter ==4'h9 && rounds_counter ==4'h3 && sub_roundcounter==4'hD)begin
            nextstate=EXPANSION_2;
 end
 if(word_counter ==4'hF && rounds_counter ==4'h3 && sub_roundcounter==4'hE)begin
            nextstate=RC_CON;
 end
 
       end  
		RC_CON: begin
   		 case (rounds_counter)
        4'b0000: round_constant = {temp2[31:24] ^ 8'h01, temp2[23:0]};
        4'b0001: round_constant = {temp2[31:24] ^ 8'h02, temp2[23:0]};
        4'b0010: round_constant = {temp2[31:24] ^ 8'h04, temp2[23:0]};
        4'b0011: round_constant = {temp2[31:24] ^ 8'h08, temp2[23:0]};
        4'b0100: round_constant = {temp2[31:24] ^ 8'h10, temp2[23:0]};
        4'b0101: round_constant = {temp2[31:24] ^ 8'h20, temp2[23:0]};
        4'b0110: round_constant = {temp2[31:24] ^ 8'h40, temp2[23:0]};
       
    endcase

    if (sub_roundcounter == 4'h4 ||sub_roundcounter==4'h8||sub_roundcounter==4'hC) begin
        nextstate = EXPANSION_1;
    end else begin
        nextstate = EXPANSION_3;
    end
end

	EXPANSION_3: begin
		sub_roundcounter =sub_roundcounter+1;
    expansion3[31:0]  = expansion1[31:0] ^ round_constant;
    expansion3[63:32] = expansion1[63:32] ^ expansion3[31:0];
    expansion3[95:64] = expansion1[95:64] ^ expansion3[63:32];
    expansion3[127:96] = expansion1[127:96] ^ expansion3[95:64];
    
 
    rot = expansion3[127:96];
    sub_counter = 2'b00;
 
    
	   if (sub_roundcounter ==4'h3) begin
        round3_result = expansion3;
    end
    if (sub_roundcounter==4'h7) begin
        round7_result=expansion3;
    end
    if (sub_roundcounter==4'hB) begin
        round11_result=expansion3;
    end
    if (sub_roundcounter==4'hF) begin
        round15_result=expansion3;
        nextstate=DONE;
    end
    else begin
 
		nextstate = SUB_BYTE;
    end
end

	EXPANSION_4: begin
		    sub_roundcounter = sub_roundcounter + 1;

    expansion4[31:0]  = expansion2[31:0] ^ temp2;
    expansion4[63:32] = expansion2[63:32] ^ expansion4[31:0];
    expansion4[95:64] = expansion2[95:64] ^ expansion4[63:32];
    expansion4[127:96] = expansion2[127:96] ^ expansion4[95:64];

    if (rounds_counter == 1'b0) begin
        round4_result = expansion4;
    end
    if (rounds_counter==1'b1) begin
        round8_result =expansion4;
    end
    if (rounds_counter==4'h2) begin
        round12_result =expansion4;
    end


    if (sub_roundcounter == 4'h4 ||sub_roundcounter ==4'h8||sub_roundcounter==4'hc) begin
        rounds_counter = rounds_counter + 1;
    end

    temp = expansion4[127:96];
    nextstate = ROT_BYTE;
end

	
        endcase
      end



// i've to implement a logiC THAT IF round counter is zero and sub_roundcounter =4'h2 and word_counter=4'h8 then next state would be RC_CON and if IF round counter is zero and sub_roundcounter =4'h3 and word counter ==4'hd next state == expansion 4;
// and IF round counter is 1 and sub_roundcounter =4'h4 and word_counter=4'h4 and then next state would be RC_CON and if IF round counter is 1 and sub_roundcounter =4'h5 and word counter ==4'ha next state == expansion 2;



endmodule

updatedkeyexpansion_tb.v
module updatedkeyexpansion_tb;

    // Testbench signals
    reg clk;
    reg rst;
    reg [255:0] key;
    wire [127:0] out_key;

    // Instantiate the keyexpansion module
    updatedkeyexpansion uut (
        .key(key),
        .clk(clk),
        .rst(rst),
        .out_key(out_key)
    );

    // Clock generation
    initial begin
        clk = 0;
        forever #5 clk = ~clk; // 10ns period
    end

    // Test sequence
    initial begin
        // Initialize inputs
        rst = 1;
        key = 256'h642423baa95efb4362d3f2ce993c0904150f258aa1fe796841d7b4429c9b5a30
;

        // Reset the system
        #10;
        rst = 0;
        #10;
        // rst = 1;

        // Apply test vectors
        #1000; // Run simulation for some time

        // End simulation
        $finish;
        
    end

    // Waveform dump
    initial begin
        $dumpfile("updatedkeyexpansion.vcd");
        $dumpvars(0,updatedkeyexpansion_tb);
    end

 endmodule
// iverilog -o updatedkeyexpansion.out updatedkeyexpansion.v updatedkeyexpansion_tb.v
// vvp updatedkeyexpansion.out
// gtkwave updatedkeyexpansion.vcd

updatedkeyexpansion.vcd
$date
	Wed Jul 24 11:46:51 2024
$end
$version
	Icarus Verilog
$end
$timescale
	1s
$end
$scope module updatedkeyexpansion_tb $end
$var wire 128 ! out_key [127:0] $end
$var reg 1 " clk $end
$var reg 256 # key [255:0] $end
$var reg 1 $ rst $end
$scope module uut $end
$var wire 1 " clk $end
$var wire 256 % key [255:0] $end
$var wire 1 $ rst $end
$var parameter 4 & DONE $end
$var parameter 4 ' EXPANSION_1 $end
$var parameter 4 ( EXPANSION_2 $end
$var parameter 4 ) EXPANSION_3 $end
$var parameter 4 * EXPANSION_4 $end
$var parameter 4 + IDLE $end
$var parameter 4 , RC_CON $end
$var parameter 4 - ROT_BYTE $end
$var parameter 4 . START $end
$var parameter 4 / SUB_BYTE $end
$var parameter 4 0 XOR $end
$var reg 128 1 expansion1 [127:0] $end
$var reg 128 2 expansion2 [127:0] $end
$var reg 128 3 expansion3 [127:0] $end
$var reg 128 4 expansion4 [127:0] $end
$var reg 256 5 key_in [255:0] $end
$var reg 5 6 nextstate [4:0] $end
$var reg 128 7 out_key [127:0] $end
$var reg 32 8 rot [31:0] $end
$var reg 128 9 round10_result [127:0] $end
$var reg 128 : round11_result [127:0] $end
$var reg 128 ; round12_result [127:0] $end
$var reg 128 < round13_result [127:0] $end
$var reg 128 = round14_result [127:0] $end
$var reg 128 > round15_result [127:0] $end
$var reg 128 ? round1_result [127:0] $end
$var reg 128 @ round2_result [127:0] $end
$var reg 128 A round3_result [127:0] $end
$var reg 128 B round4_result [127:0] $end
$var reg 128 C round5_result [127:0] $end
$var reg 128 D round6_result [127:0] $end
$var reg 128 E round7_result [127:0] $end
$var reg 128 F round8_result [127:0] $end
$var reg 128 G round9_result [127:0] $end
$var reg 32 H round_constant [31:0] $end
$var reg 4 I rounds_counter [3:0] $end
$var reg 2 J second_subcounter [1:0] $end
$var reg 5 K state [4:0] $end
$var reg 32 L sub [31:0] $end
$var reg 2 M sub_counter [1:0] $end
$var reg 4 N sub_roundcounter [3:0] $end
$var reg 32 O temp [31:0] $end
$var reg 32 P temp2 [31:0] $end
$var reg 4 Q word_counter [3:0] $end
$upscope $end
$upscope $end
$enddefinitions $end
$comment Show the parameter values. $end
$dumpall
b1010 0
b1000 /
b10 .
b111 -
b1001 ,
b1 +
b110 *
b101 )
b100 (
b11 '
b1011 &
$end
#0
$dumpvars
bx Q
bx P
bx O
b0 N
bx M
bx L
bx K
bx J
b0 I
b0 H
bx G
bx F
bx E
bx D
bx C
bx B
bx A
bx @
bx ?
bx >
bx =
bx <
bx ;
bx :
bx 9
bx 8
bx 7
b0 6
bx 5
bx 4
bx 3
bx 2
bx 1
b110010000100100001000111011101010101001010111101111101101000011011000101101001111110010110011101001100100111100000010010000010000010101000011110010010110001010101000011111111001111001011010000100000111010111101101000100001010011100100110110101101000110000 %
1$
b110010000100100001000111011101010101001010111101111101101000011011000101101001111110010110011101001100100111100000010010000010000010101000011110010010110001010101000011111111001111001011010000100000111010111101101000100001010011100100110110101101000110000 #
0"
bx !
$end
#5
b10 6
b0 J
b0 M
b0 Q
b1 K
1"
#10
0"
0$
#15
b11 6
b110010000100100001000111011101010101001010111101111101101000011011000101101001111110010110011101001100100111100000010010000010000010101000011110010010110001010101000011111111001111001011010000100000111010111101101000100001010011100100110110101101000110000 5
b1 J
b1 M
b1 Q
b10 K
1"
#20
0"
#25
b100 6
b10101000011110010010110001010101000011111111001111001011010000100000111010111101101000100001010011100100110110101101000110000 ?
b10101000011110010010110001010101000011111111001111001011010000100000111010111101101000100001010011100100110110101101000110000 1
b1 N
b10 J
b10 M
b10 Q
b11 K
1"
#30
0"
#35
b111 6
b1100100001001000010001110111010101010010101111011111011010000110110001011010011111100101100111010011001001111000000100100000100 @
b1100100001001000010001110111010 O
b1100100001001000010001110111010101010010101111011111011010000110110001011010011111100101100111010011001001111000000100100000100 2
b10 N
b11 J
b11 M
b11 Q
b100 K
1"
#40
0"
#45
b1000 6
b100100001000111011101001100100 8
b0 J
b0 M
b100 Q
b111 K
1"
#50
0"
#55
b100100001000111011101000000000 O
b1000011xxxxxxxxxxxxxxxxxxxxxxxx P
b1001000010001110111010 8
b1000011 L
b1 J
b1 M
b101 Q
b1000 K
1"
#60
0"
#65
b100011101110100000000000000000 O
b1111010001000011xxxxxxxxxxxxxxxx P
b10010000100011 8
b11110100 L
b10 J
b10 M
b110 Q
1"
#70
0"
#75
b10111010000000000000000000000000 O
b1001101111010001000011xxxxxxxx P
b100100 8
b100110 L
b11 J
b11 M
b111 Q
1"
#80
0"
#85
b1001 6
b0 O
b110110001001101111010001000011 P
b0 8
b110110 L
b0 J
b0 M
b1000 Q
1"
#90
0"
#95
b101 6
b110111001001101111010001000011 H
b1 J
b1 M
b1001 Q
b1001 K
1"
#100
0"
#105
b1000 6
b1011110100110110100011011010011010010111001010001100011010110011110101001101010000110100011000110101011101111011010111001110011 A
b1011110100110110100011011010011 8
b1011110100110110100011011010011010010111001010001100011010110011110101001101010000110100011000110101011101111011010111001110011 3
b11 N
b10 J
b0 M
b1010 Q
b101 K
1"
#110
0"
#115
b1100110001101100010011011110100 P
b10111101001101101000110 8
b1100110 L
b1 J
b1 M
b1011 Q
b1000 K
1"
#120
0"
#125
b1011010011001100011011000100110 P
b101111010011011 8
b1011010 L
b10 J
b10 M
b1100 Q
1"
#130
0"
#135
b10100010110100110011000110110 P
b1011110 8
b10100 L
b11 J
b11 M
b1101 Q
1"
#140
0"
#145
b110 6
b1011000000101000101101001100110 P
b0 8
b1011000 L
b0 J
b0 M
b1110 Q
1"
#150
0"
#155
b111 6
b1101110100000010111100101010101 O
b1 I
b1101110100000010111100101010101000010101010010101011010111011111010001111111011101000011010110011000001001010000101001101100010 B
b1101110100000010111100101010101000010101010010101011010111011111010001111111011101000011010110011000001001010000101001101100010 4
b100 N
b1 J
b1 M
b1111 Q
b110 K
1"
#160
0"
#165
b1000 6
b10000001011110010101010101101110 8
b10 J
b0 M
b0 Q
b111 K
1"
#170
0"
#175
b10000001011110010101010100000000 O
b10011111010110000001010001011010 P
b100000010111100101010101 8
b10011111 L
b1 J
b1 M
b1 Q
b1000 K
1"
#180
0"
#185
b1111001010101010000000000000000 O
b11111100100111110101100000010100 P
b1000000101111001 8
b11111100 L
b10 J
b10 M
b10 Q
1"
#190
0"
#195
b1010101000000000000000000000000 O
b10110110111111001001111101011000 P
b10000001 8
b10110110 L
b11 J
b11 M
b11 Q
1"
#200
0"
#205
b1001 6
b0 O
b1100101101101111110010011111 P
b0 8
b1100 L
b0 J
b0 M
b100 Q
1"
#210
0"
#215
b11 6
b1110101101101111110010011111 H
b1 J
b1 M
b101 Q
b1001 K
1"
#220
0"
#225
b1000 6
b1011000011011100110110101010111 8
b1011000011011100110110101010111000001101111010100101011100001000100110101100001010010001101110110100111000010110101001011101100 C
b1011000011011100110110101010111000001101111010100101011100001000100110101100001010010001101110110100111000010110101001011101100 1
b101 N
b0 J
b10 M
b110 Q
b11 K
1"
#230
0"
#235
b1011011000011001011011011111100 P
b10110000110111001101101 8
b1011011 L
b11 J
b11 M
b111 Q
b1000 K
1"
#240
0"
#245
b111100010110110000110010110110 P
b101100001101110 8
b111100 L
b0 J
b0 M
b1000 Q
1"
#250
0"
#255
b10011111001111000101101100001100 P
b1011000 8
b10011111 L
b1 J
b1 M
b1001 Q
1"
#260
0"
#265
b100 6
b1101010100111110011110001011011 P
b0 8
b1101010 L
b10 J
b10 M
b1010 Q
1"
#270
0"
#275
b111 6
b1101100011010001110110100101111 O
b1101100011010001110110100101111000000101110100110010100011110100000100001001100110011101001010110101011101101110110111100111001 D
b1101100011010001110110100101111000000101110100110010100011110100000100001001100110011101001010110101011101101110110111100111001 2
b110 N
b11 J
b11 M
b1011 Q
b100 K
1"
#280
0"
#285
b1000 6
b1101000111011010010111101101100 8
b0 J
b0 M
b1100 Q
b111 K
1"
#290
0"
#295
b1101000111011010010111100000000 O
b1010000011010101001111100111100 P
b11010001110110100101111 8
b1010000 L
b1 J
b1 M
b1101 Q
b1000 K
1"
#300
0"
#305
b11101101001011110000000000000000 O
b10101010100000110101010011111 P
b110100011101101 8
b10101 L
b10 J
b10 M
b1110 Q
1"
#310
0"
#315
b101111000000000000000000000000 O
b1010101000101010101000001101010 P
b1101000 8
b1010101 L
b11 J
b11 M
b1111 Q
1"
#320
0"
#325
b1001 6
b0 O
b1000101010101010001010101010000 P
b0 8
b1000101 L
b0 J
b0 M
b0 Q
1"
#330
0"
#335
b101 6
b1000111010101010001010101010000 H
b1 J
b1 M
b1 Q
b1001 K
1"
#340
0"
#345
b1000 6
b11110011101001000100100110110010101010111100101000100100111001011010110100111111000011110110000111100000010111100100011110111100 E
b11110011101001000100100110110010 8
b11110011101001000100100110110010101010111100101000100100111001011010110100111111000011110110000111100000010111100100011110111100 3
b111 N
b10 J
b0 M
b10 Q
b101 K
1"
#350
0"
#355
b110111010001010101010100010101 P
b111100111010010001001001 8
b110111 L
b1 J
b1 M
b11 Q
b1000 K
1"
#360
0"
#365
b111011001101110100010101010101 P
b1111001110100100 8
b111011 L
b10 J
b10 M
b100 Q
1"
#370
0"
#375
b1001001001110110011011101000101 P
b11110011 8
b1001001 L
b11 J
b11 M
b101 Q
1"
#380
0"
#385
b110 6
b1101010010010011101100110111 P
b0 8
b1101 L
b0 J
b0 M
b110 Q
1"
#390
0"
#395
b111 6
b11000000001100111110001111001110 O
b10 I
b11000000001100111110001111001110101011000101101100001110111000011010111010110010100110101001101110100110111111100101010000001110 F
b11000000001100111110001111001110101011000101101100001110111000011010111010110010100110101001101110100110111111100101010000001110 4
b1000 N
b1 J
b1 M
b111 Q
b110 K
1"
#400
0"
#405
b1000 6
b110011111000111100111011000000 8
b10 J
b0 M
b1000 Q
b111 K
1"
#410
0"
#415
b110011111000111100111000000000 O
b10111010000011010100100100111011 P
b1100111110001111001110 8
b10111010 L
b1 J
b1 M
b1001 Q
b1000 K
1"
#420
0"
#425
b11100011110011100000000000000000 O
b10001011101110100000110101001001 P
b11001111100011 8
b10001011 L
b10 J
b10 M
b1010 Q
1"
#430
0"
#435
b11001110000000000000000000000000 O
b10001100010111011101000001101 P
b110011 8
b10001 L
b11 J
b11 M
b1011 Q
1"
#440
0"
#445
b11 6
b0 O
b11000011000100011000101110111010 P
b0 8
b11000011 L
b0 J
b0 M
b1100 Q
1"
#450
0"
#455
b1000 6
b11010110000111101010111000110000 8
b11010110000111101010111000110000001001011011101011100111100000101000111001110000110000110110011100100011010011111100110000000110 G
b11010110000111101010111000110000001001011011101011100111100000101000111001110000110000110110011100100011010011111100110000000110 1
b1001 N
b0 J
b1 M
b1101 Q
b11 K
1"
#460
0"
#465
b100110000110001000110001011 P
b110101100001111010101110 8
b100 L
b10 J
b10 M
b1110 Q
b1000 K
1"
#470
0"
#475
b11100100000001001100001100010001 P
b1101011000011110 8
b11100100 L
b11 J
b11 M
b1111 Q
1"
#480
0"
#485
b1110010111001000000010011000011 P
b11010110 8
b1110010 L
b0 J
b0 M
b0 Q
1"
#490
0"
#495
b100 6
b11110110011100101110010000000100 P
b0 8
b11110110 L
b1 J
b1 M
b1 Q
1"
#500
0"
